[
    {
        "id": "hypostatization_0",
        "rhetorical_device": [
            "hypostatization"
        ],
        "text": "天文台のドームが開くと、星を追う望遠鏡は巨大な昆虫の触覚のように空を探っていた。"
    },
    {
        "id": "hypostatization_1",
        "rhetorical_device": [
            "hypostatization"
        ],
        "text": "アイスクリームショップのオーナーは、冷凍庫のように冷たい態度で従業員を扱った。"
    },
    {
        "id": "hypostatization_2",
        "rhetorical_device": [
            "hypostatization"
        ],
        "text": "宇宙飛行士たちは、まるで地球という巨大な青い宝石を守る騎士のようだった。"
    },
    {
        "id": "hypostatization_3",
        "rhetorical_device": [
            "hypostatization"
        ],
        "text": "動画編集ソフトの前に座る彼は、まるで時計の歯車のように正確に、カットとカットをつなぎ合わせていった。"
    },
    {
        "id": "hypostatization_4",
        "rhetorical_device": [
            "hypostatization"
        ],
        "text": "古文書を扱う彼女の手つきは、まるで脆い氷を扱うかのように繊細で慎重だった。"
    },
    {
        "id": "hypostatization_5",
        "rhetorical_device": [
            "hypostatization"
        ],
        "text": "彼女の指は、ろくろの上で踊る蝶のようだった。粘土は彼女の意志に従い、美しい花瓶へと姿を変えていった。"
    },
    {
        "id": "hypostatization_6",
        "rhetorical_device": [
            "hypostatization"
        ],
        "text": "祖母の手作りキルトは、まるで時を閉じ込めた タイムカプセルのようだった。"
    },
    {
        "id": "hypostatization_7",
        "rhetorical_device": [
            "hypostatization"
        ],
        "text": "ドラマセラピーの最中、彼女は感情を表に出さず、まるで氷の彫刻のように冷たく座っていた。"
    },
    {
        "id": "hypostatization_8",
        "rhetorical_device": [
            "hypostatization"
        ],
        "text": "会議室の空気は鉛のように重く、誰も口を開こうとしない。対立する意見の間で、参加者たちは氷のように凍りついていた。"
    },
    {
        "id": "hypostatization_9",
        "rhetorical_device": [
            "hypostatization"
        ],
        "text": "天文クラブの新入生たちは、初めて見る星空の前で石像のように動かなかった。"
    },
    {
        "id": "hypostatization_10",
        "rhetorical_device": [
            "hypostatization"
        ],
        "text": "陶芸家の手は、粘土を扱う時、まるで魔法の杖のように動いた。無機質な土から、生命力溢れる作品が生まれていく。"
    },
    {
        "id": "hypostatization_11",
        "rhetorical_device": [
            "hypostatization"
        ],
        "text": "endless highwayは、大地を縫う糸のように、地平線まで真っすぐに伸びていた。"
    },
    {
        "id": "hypostatization_12",
        "rhetorical_device": [
            "hypostatization"
        ],
        "text": "大人の学習教室で、新しい知識を吸収する生徒たちは、まるでスポンジのように、情報を吸い取っていった。"
    },
    {
        "id": "hypostatization_13",
        "rhetorical_device": [
            "hypostatization"
        ],
        "text": "キルティング教室の生徒たちは、糸と布を操る器用な機械のように、黙々と作業に没頭していた。"
    },
    {
        "id": "hypostatization_14",
        "rhetorical_device": [
            "hypostatization"
        ],
        "text": "保護猫たちは、まるで愛情の渇きを癒す砂漠のオアシスのように、里親を待ち望んでいた。"
    },
    {
        "id": "hypostatization_15",
        "rhetorical_device": [
            "hypostatization"
        ],
        "text": "哲学の講義を受ける学生たちは、まるで石像のように動かず、教授の言葉を吸収していった。"
    },
    {
        "id": "hypostatization_16",
        "rhetorical_device": [
            "hypostatization"
        ],
        "text": "詩人の言葉は鋭利な刃物のようだった。一つ一つの単語が心に深く刻まれ、読者の魂を切り裂いていく。"
    },
    {
        "id": "hypostatization_17",
        "rhetorical_device": [
            "hypostatization"
        ],
        "text": "宇宙ステーションの乗組員たちは、まるで巨大な金属の殻に閉じ込められた隠者のようだった。"
    },
    {
        "id": "hypostatization_18",
        "rhetorical_device": [
            "hypostatization"
        ],
        "text": "サプライズパーティーの準備をしている友人たちは、主役が来るまで家具のように静かに待機した。"
    },
    {
        "id": "hypostatization_19",
        "rhetorical_device": [
            "hypostatization"
        ],
        "text": "新しい技術は、古い産業を砂のように侵食していった。"
    },
    {
        "id": "hypostatization_20",
        "rhetorical_device": [
            "hypostatization"
        ],
        "text": "彼の鬱は、まるで濃霧のように彼の心を覆い、周囲の景色を曇らせていた。"
    },
    {
        "id": "hypostatization_21",
        "rhetorical_device": [
            "hypostatization"
        ],
        "text": "戦争で家族を失った彼女の目は、まるでガラス玉のように虚ろで、何も映していなかった。"
    },
    {
        "id": "hypostatization_22",
        "rhetorical_device": [
            "hypostatization"
        ],
        "text": "チューリップの球根を植える彼女の姿は、まるで大地に宝石を埋める宝石商のようだった。"
    },
    {
        "id": "hypostatization_23",
        "rhetorical_device": [
            "hypostatization"
        ],
        "text": "シルク絵画を描く彼女の筆さばきは、まるで蝶が花から花へ舞うかのように軽やかだった。"
    },
    {
        "id": "hypostatization_24",
        "rhetorical_device": [
            "hypostatization"
        ],
        "text": "コンサートの準備に追われるスタッフたちは、まるで巨大な舞台装置の歯車のように、黙々と仕事をこなしていった。"
    },
    {
        "id": "hypostatization_25",
        "rhetorical_device": [
            "hypostatization"
        ],
        "text": "エコカーの静かなエンジン音は、まるで猫の忍び足のようだった。"
    },
    {
        "id": "hypostatization_26",
        "rhetorical_device": [
            "hypostatization"
        ],
        "text": "平和構築の道のりは、まるで砂漠の中の一粒の砂のように、時に見失いそうになる。"
    },
    {
        "id": "hypostatization_27",
        "rhetorical_device": [
            "hypostatization"
        ],
        "text": "シェフの包丁さばきは機械のように正確で、野菜を切る音が厨房に響き渡った。"
    },
    {
        "id": "hypostatization_28",
        "rhetorical_device": [
            "hypostatization"
        ],
        "text": "絹布に染料を塗る彼の動きは、まるで蜂が花粉を運ぶかのように、慎重で計算されていた。"
    },
    {
        "id": "hypostatization_29",
        "rhetorical_device": [
            "hypostatization"
        ],
        "text": "アフリカのサバンナを走る観光客たちは、まるで砂漠の中を進む時計の歯車のようだった。"
    },
    {
        "id": "hypostatization_30",
        "rhetorical_device": [
            "hypostatization"
        ],
        "text": "ロックフェスのモッシュピットは、まるで荒れ狂う海のようだった。人々は波に飲み込まれ、激しく揺さぶられていた。"
    },
    {
        "id": "hypostatization_31",
        "rhetorical_device": [
            "hypostatization"
        ],
        "text": "スケートパークで新しい技に挑戦する彼は、まるでゼンマイ仕掛けのおもちゃのように何度も同じ動きを繰り返した。"
    },
    {
        "id": "hypostatization_32",
        "rhetorical_device": [
            "hypostatization"
        ],
        "text": "彼の心は、長年の失恋で石のように固くなっていた。どんな優しい言葉も、その堅い殻を破ることはできなかった。"
    },
    {
        "id": "hypostatization_33",
        "rhetorical_device": [
            "hypostatization"
        ],
        "text": "文化人類学の講義中、学生たちは教授の言葉を吸収しようと、スポンジのように静かに座っていた。"
    },
    {
        "id": "hypostatization_34",
        "rhetorical_device": [
            "hypostatization"
        ],
        "text": "インディーゲーム開発者たちは、大手企業の圧倒的な力の前に、まるでチェス盤上の弱い駒のように、次々と市場から消えていった。"
    },
    {
        "id": "hypostatization_35",
        "rhetorical_device": [
            "hypostatization"
        ],
        "text": "都市農業に携わる若者たちは、アスファルトの海に浮かぶ緑の島のようだった。"
    },
    {
        "id": "hypostatization_36",
        "rhetorical_device": [
            "hypostatization"
        ],
        "text": "絶滅危惧種の動物たちは、まるで生きた化石のように、現代の世界に取り残されていた。"
    },
    {
        "id": "hypostatization_37",
        "rhetorical_device": [
            "hypostatization"
        ],
        "text": "マチュピチュの遺跡に立つと、まるで歴史という重い本の一ページに自分が挟まれているような感覚に襲われた。"
    },
    {
        "id": "hypostatization_38",
        "rhetorical_device": [
            "hypostatization"
        ],
        "text": "山奥で珍しい山菜を見つけた瞬間、彼の目は宝石のように輝き、体は岩のように硬直した。"
    },
    {
        "id": "hypostatization_39",
        "rhetorical_device": [
            "hypostatization"
        ],
        "text": "その日の朝、彼女は目覚まし時計のように正確に起き上がった。朝のルーティンをこなす姿は、まるで精密機械のようだった。"
    },
    {
        "id": "hypostatization_40",
        "rhetorical_device": [
            "hypostatization"
        ],
        "text": "熱気球のパイロットは、大空の海図を読む航海士のように、風の流れを読み取っていた。"
    },
    {
        "id": "hypostatization_41",
        "rhetorical_device": [
            "hypostatization"
        ],
        "text": "刑事は証拠を前に石像のように動かなかった。その目は真実を見抜こうと、まるで探査機のように犯人の顔を走査していた。"
    },
    {
        "id": "hypostatization_42",
        "rhetorical_device": [
            "hypostatization"
        ],
        "text": "チームのモチベーションは、まるで風見鶏のように外部の影響で簡単に方向を変えてしまう。"
    },
    {
        "id": "hypostatization_43",
        "rhetorical_device": [
            "hypostatization"
        ],
        "text": "コンポストの匂いは、まるで大地の呼吸のように、庭全体に広がっていった。"
    },
    {
        "id": "hypostatization_44",
        "rhetorical_device": [
            "hypostatization"
        ],
        "text": "病院の待合室で、患者たちは不安に震える木の葉のように座っていた。"
    },
    {
        "id": "hypostatization_45",
        "rhetorical_device": [
            "hypostatization"
        ],
        "text": "宇宙飛行士たちは、無重力空間で浮遊する彫像のように、静かに任務を遂行していた。"
    },
    {
        "id": "hypostatization_46",
        "rhetorical_device": [
            "hypostatization"
        ],
        "text": "陶芸家の指先から生まれる作品は、まるで土が魂を吹き込まれたかのようだった。無機質な粘土が、生命を宿した芸術へと変貌していく。"
    },
    {
        "id": "hypostatization_47",
        "rhetorical_device": [
            "hypostatization"
        ],
        "text": "有機農法を実践する農家は、化学肥料を使う隣人たちの中で、まるで鉄の意志を持つ孤島のように、毅然と立っていた。"
    },
    {
        "id": "hypostatization_48",
        "rhetorical_device": [
            "hypostatization"
        ],
        "text": "彼のボランティア精神は、まるで灯台のように、周りの人々を導く光となっていた。"
    },
    {
        "id": "hypostatization_49",
        "rhetorical_device": [
            "hypostatization"
        ],
        "text": "彼女の表情は、まるで大理石の彫刻のように冷たく、感情を読み取ることができなかった。"
    },
    {
        "id": "hypostatization_50",
        "rhetorical_device": [
            "hypostatization"
        ],
        "text": "人類学の講義で、教授は学生たちを前に石像のように厳かな姿勢を保ち続けた。"
    },
    {
        "id": "hypostatization_51",
        "rhetorical_device": [
            "hypostatization"
        ],
        "text": "伝統芸能の舞台で、演者たちは人形のように正確な動きを繰り返していた。彼らの表情は能面のように無機質で、感情を読み取ることはできなかった。"
    },
    {
        "id": "hypostatization_52",
        "rhetorical_device": [
            "hypostatization"
        ],
        "text": "バーベキューの煙に包まれた彼は、まるで霧の中の幽霊のように立っていた。"
    },
    {
        "id": "hypostatization_53",
        "rhetorical_device": [
            "hypostatization"
        ],
        "text": "街角に立つ人々は、まるでチェスの駒のように、都市という盤上で動かされているようだった。"
    },
    {
        "id": "hypostatization_54",
        "rhetorical_device": [
            "hypostatization"
        ],
        "text": "バレエ教室の生徒たちは、厳しい練習に耐え、まるで炎の中で鍛えられる鋼のように強くしなやかになっていった。汗は宝石のように輝いていた。"
    },
    {
        "id": "hypostatization_55",
        "rhetorical_device": [
            "hypostatization"
        ],
        "text": "アドベンチャーレースのコースは、まるで生きているかのように、選手たちを翻弄した。険しい山々は、まるで巨人のように立ちはだかり、選手たちの前進を阻んだ。"
    },
    {
        "id": "hypostatization_56",
        "rhetorical_device": [
            "hypostatization"
        ],
        "text": "アジア旅行中、彼は言葉の壁に阻まれ、まるで無人島に取り残された人形のように孤独を感じた。"
    },
    {
        "id": "hypostatization_57",
        "rhetorical_device": [
            "hypostatization"
        ],
        "text": "ジオキャッシングに熱中するあまり、彼らは宝箱のように無機質な存在になっていった。"
    },
    {
        "id": "hypostatization_58",
        "rhetorical_device": [
            "hypostatization"
        ],
        "text": "予防医学の重要性を説く医師の言葉は、まるで鉄の壁のように堅固で揺るぎなかった。"
    },
    {
        "id": "hypostatization_59",
        "rhetorical_device": [
            "hypostatization"
        ],
        "text": "パーティー会場に入った瞬間、彼女は蝋人形のように固まってしまった。予想外の出来事に驚いたのだ。"
    },
    {
        "id": "hypostatization_60",
        "rhetorical_device": [
            "hypostatization"
        ],
        "text": "針と糸を操る彼女の手は、精密機械のように正確で迅速だった。"
    },
    {
        "id": "hypostatization_61",
        "rhetorical_device": [
            "hypostatization"
        ],
        "text": "バランスを取る岩は、まるで重力を無視する魔法使いのようだった。"
    },
    {
        "id": "hypostatization_62",
        "rhetorical_device": [
            "hypostatization"
        ],
        "text": "手芸教室の生徒たちは、糸と針を操る様子があまりにも流暢で、まるで織機の部品のようだった。"
    },
    {
        "id": "hypostatization_63",
        "rhetorical_device": [
            "hypostatization"
        ],
        "text": "その医師の診断は、患者の体を透視するX線のように、病気の本質を見抜いていった。"
    },
    {
        "id": "hypostatization_64",
        "rhetorical_device": [
            "hypostatization"
        ],
        "text": "保護猫を抱きしめた瞬間、それまで鉄のように固かった彼女の表情が、柔らかな布のようにほころんだ。"
    },
    {
        "id": "hypostatization_65",
        "rhetorical_device": [
            "hypostatization"
        ],
        "text": "ボランティア消防士たちは、炎の中へ岩のように揺るぎない決意で突入していった。"
    },
    {
        "id": "hypostatization_66",
        "rhetorical_device": [
            "hypostatization"
        ],
        "text": "新しいレシピを考え出す彼の頭脳は、まるで複雑な方程式を解く計算機のようだった。"
    },
    {
        "id": "hypostatization_67",
        "rhetorical_device": [
            "hypostatization"
        ],
        "text": "写真展で彼女は一枚の写真の前に立ち尽くした。まるで美術館の彫像のように動かず、その姿は作品の一部と化していた。"
    },
    {
        "id": "hypostatization_68",
        "rhetorical_device": [
            "hypostatization"
        ],
        "text": "SNSの世界では、ユーザーたちは単なるデータの点として扱われ、アルゴリズムの海を漂う無力な浮遊物のようだった。"
    },
    {
        "id": "hypostatization_69",
        "rhetorical_device": [
            "hypostatization"
        ],
        "text": "デザイン会議で意見が対立した瞬間、部屋の空気は鋭い刃物のように張り詰めた。誰もが自分の主張を譲らず、緊張感が漂っていた。"
    },
    {
        "id": "hypostatization_70",
        "rhetorical_device": [
            "hypostatization"
        ],
        "text": "新しい理論を発表した彼は、科学界の地殻を揺るがす地震のような存在だった。"
    },
    {
        "id": "hypostatization_71",
        "rhetorical_device": [
            "hypostatization"
        ],
        "text": "消防団の新人たちは、訓練の厳しさに、まるで鉄の棒のように硬直していた。"
    },
    {
        "id": "hypostatization_72",
        "rhetorical_device": [
            "hypostatization"
        ],
        "text": "アジアの街並みを歩いていると、彼らは まるで時間が氷結したかのような古い町並みに出くわした。"
    },
    {
        "id": "hypostatization_73",
        "rhetorical_device": [
            "hypostatization"
        ],
        "text": "低炭素経済への移行は、まるで巨大な船の方向転換のように、ゆっくりと確実に進んでいた。"
    },
    {
        "id": "hypostatization_74",
        "rhetorical_device": [
            "hypostatization"
        ],
        "text": "データの山を前に、彼は鉄の意志で立ち向かい、グラフや図表を作り上げていった。"
    },
    {
        "id": "hypostatization_75",
        "rhetorical_device": [
            "hypostatization"
        ],
        "text": "ステージに立つバンドメンバーは、観客の熱気を吸い込む巨大な磁石のようだった。"
    },
    {
        "id": "hypostatization_76",
        "rhetorical_device": [
            "hypostatization"
        ],
        "text": "マイクロブルワリーのオーナーは、発酵タンクを前に立ち尽くし、まるで時計仕掛けのように正確に時間を計っていた。"
    },
    {
        "id": "hypostatization_77",
        "rhetorical_device": [
            "hypostatization"
        ],
        "text": "彼女の編集技術は鋭い刃物のようで、不要なシーンを容赦なく切り落としていった。"
    },
    {
        "id": "hypostatization_78",
        "rhetorical_device": [
            "hypostatization"
        ],
        "text": "ベジタリアンレストランのシェフの手さばきは、まるで野菜と対話しているかのようだった。包丁が空気を切る音が、静かな調理場に響く。"
    },
    {
        "id": "hypostatization_79",
        "rhetorical_device": [
            "hypostatization"
        ],
        "text": "釣り大会の参加者たちは、まるで岩のように動かず、水面を見つめ続けていた。"
    },
    {
        "id": "hypostatization_80",
        "rhetorical_device": [
            "hypostatization"
        ],
        "text": "茶葉をブレンドする彼の感覚は、まるで精密な計量器のように正確で、ミリグラム単位の違いも見逃さなかった。"
    },
    {
        "id": "hypostatization_81",
        "rhetorical_device": [
            "hypostatization"
        ],
        "text": "彼女のパントマイムは見事だった。まるで透明なガラスの壁に囲まれているかのように、観客を魅了した。"
    },
    {
        "id": "hypostatization_82",
        "rhetorical_device": [
            "hypostatization"
        ],
        "text": "フラッシュモブの終了と同時に、人々は氷が溶けるように四散していった。"
    },
    {
        "id": "hypostatization_83",
        "rhetorical_device": [
            "hypostatization"
        ],
        "text": "遺伝子治療を受けた患者たちは、まるで書き換えられた本のようだった。彼らの体は新しい物語を紡ぎ始めていた。"
    },
    {
        "id": "hypostatization_84",
        "rhetorical_device": [
            "hypostatization"
        ],
        "text": "宇宙飛行士たちは、真空の海に浮かぶ金属の島のように、静かに宇宙ステーションを操縦していた。"
    },
    {
        "id": "hypostatization_85",
        "rhetorical_device": [
            "hypostatization"
        ],
        "text": "再生可能エネルギーの普及は、まるで氷河のように遅々として進まない。"
    },
    {
        "id": "hypostatization_86",
        "rhetorical_device": [
            "hypostatization"
        ],
        "text": "バレエの練習に励む生徒たちは、まるで精密機械のように、教師の指示に従って動いていた。"
    },
    {
        "id": "hypostatization_87",
        "rhetorical_device": [
            "hypostatization"
        ],
        "text": "コンサート会場に集まった観客は、まるで蜂の巣のように整然と並んでいた。"
    },
    {
        "id": "hypostatization_88",
        "rhetorical_device": [
            "hypostatization"
        ],
        "text": "ワークライフバランスを失った彼は、まるでゼンマイ仕掛けの人形のように、機械的に日々をこなしていた。"
    },
    {
        "id": "hypostatization_89",
        "rhetorical_device": [
            "hypostatization"
        ],
        "text": "哲学的な議論に熱中する友人たちは、まるで歯車のように噛み合い、次々と新しい考えを生み出していった。"
    },
    {
        "id": "hypostatization_90",
        "rhetorical_device": [
            "hypostatization"
        ],
        "text": "ガラス工房で働く彼女の手は、長年の経験で磨かれた道具のように正確だった。"
    },
    {
        "id": "hypostatization_91",
        "rhetorical_device": [
            "hypostatization"
        ],
        "text": "遺伝子研究所の白衣の科学者たちは、まるで無機質な実験器具の一部のように、黙々と作業を続けていた。"
    },
    {
        "id": "hypostatization_92",
        "rhetorical_device": [
            "hypostatization"
        ],
        "text": "宇宙開発の歴史は、無数の星々のように輝く科学者たちの努力で彩られている。"
    },
    {
        "id": "hypostatization_93",
        "rhetorical_device": [
            "hypostatization"
        ],
        "text": "アジア旅行中、彼らは言葉の壁に阻まれ、まるで島のように孤立していた。"
    },
    {
        "id": "hypostatization_94",
        "rhetorical_device": [
            "hypostatization"
        ],
        "text": "平和会議での彼の発言は、まるで鋼鉄の壁のように強固で、誰も反論できなかった。"
    },
    {
        "id": "hypostatization_95",
        "rhetorical_device": [
            "hypostatization"
        ],
        "text": "LGBTQの権利を求めるデモ行進は、まるで虹色の川のように、街を流れていった。"
    },
    {
        "id": "hypostatization_96",
        "rhetorical_device": [
            "hypostatization"
        ],
        "text": "バレエダンサーの足は、まるで鋼鉄でできているかのように強靭で、何時間もの練習にも耐えていた。"
    },
    {
        "id": "hypostatization_97",
        "rhetorical_device": [
            "hypostatization"
        ],
        "text": "指輪作りに没頭する職人の姿は、まるで彫刻のように動きが少なかった。"
    },
    {
        "id": "hypostatization_98",
        "rhetorical_device": [
            "hypostatization"
        ],
        "text": "新しい茶葉をブレンドする際、彼は化学者のような精密さで作業を進めた。"
    },
    {
        "id": "hypostatization_99",
        "rhetorical_device": [
            "hypostatization"
        ],
        "text": "岩壁を降りる彼女の動きは、重力に逆らう蝶のようだった。"
    },
    {
        "id": "hypostatization_100",
        "rhetorical_device": [
            "hypostatization"
        ],
        "text": "伝統工芸の職人たちは、長年の経験で手が道具と一体化し、まるで木彫りの延長のような存在だった。"
    },
    {
        "id": "hypostatization_101",
        "rhetorical_device": [
            "hypostatization"
        ],
        "text": "保護犬を迎え入れた瞬間、それまで氷のように冷たかった彼の心が、少しずつ溶け始めた。"
    },
    {
        "id": "hypostatization_102",
        "rhetorical_device": [
            "hypostatization"
        ],
        "text": "異国の街を歩く観光客たちは、まるで迷路に閉じ込められたネズミのように右往左往していた。"
    },
    {
        "id": "hypostatization_103",
        "rhetorical_device": [
            "hypostatization"
        ],
        "text": "多様性を重んじる会社だと聞いていたのに、実際に入社してみると、全員が同じ型にはめられた人形のようだった。"
    },
    {
        "id": "hypostatization_104",
        "rhetorical_device": [
            "hypostatization"
        ],
        "text": "職人の手から生まれる作品は、まるで魂を吹き込まれたかのように、独特の温もりを放っていた。"
    },
    {
        "id": "hypostatization_105",
        "rhetorical_device": [
            "hypostatization"
        ],
        "text": "ダンサーたちは、音楽に合わせて動く人形のようだった。糸で操られているかのような、完璧な同調性を見せていた。"
    },
    {
        "id": "hypostatization_106",
        "rhetorical_device": [
            "hypostatization"
        ],
        "text": "コンテストの審査員たちは、参加者のケーキを機械のような正確さで切り分けていった。"
    },
    {
        "id": "hypostatization_107",
        "rhetorical_device": [
            "hypostatization"
        ],
        "text": "オーストラリアの砂漠を歩く旅人たちは、灼熱の太陽の下で岩のように固まっていった。"
    },
    {
        "id": "hypostatization_108",
        "rhetorical_device": [
            "hypostatization"
        ],
        "text": "波に乗るサーファーたちは、まるで海面に浮かぶコルクのように軽々と動いていた。"
    },
    {
        "id": "hypostatization_109",
        "rhetorical_device": [
            "hypostatization"
        ],
        "text": "溶鉱炉の前で働く作業員たちは、まるで機械の歯車のように黙々と動いていた。"
    },
    {
        "id": "hypostatization_110",
        "rhetorical_device": [
            "hypostatization"
        ],
        "text": "コンポストの中で、生ゴミは黙々と土へと変化していく。まるで、無言の錬金術師のようだ。"
    },
    {
        "id": "hypostatization_111",
        "rhetorical_device": [
            "hypostatization"
        ],
        "text": "彼らの要求は岩のように固く、会社側の説得は水のように跳ね返された。"
    },
    {
        "id": "hypostatization_112",
        "rhetorical_device": [
            "hypostatization"
        ],
        "text": "哲学者たちは、真理という巨大な山を前に、小さな石ころのように無力だった。"
    },
    {
        "id": "hypostatization_113",
        "rhetorical_device": [
            "hypostatization"
        ],
        "text": "チームビルディングの成功で、以前は鉄の壁のように冷たかった部署間の関係が溶け始めた。"
    },
    {
        "id": "hypostatization_114",
        "rhetorical_device": [
            "hypostatization"
        ],
        "text": "夜空の星々は、まるで天球儀の上に散りばめられた宝石のように、冷たく輝いていた。"
    },
    {
        "id": "hypostatization_115",
        "rhetorical_device": [
            "hypostatization"
        ],
        "text": "映画の場面転換は、まるで砂時計の砂が落ちるように滑らかだった。"
    },
    {
        "id": "hypostatization_116",
        "rhetorical_device": [
            "hypostatization"
        ],
        "text": "洞窟の奥深くで、探検家たちは暗闇に溶け込む影のようになった。その存在が、岩肌と一体化していくようだった。"
    },
    {
        "id": "hypostatization_117",
        "rhetorical_device": [
            "hypostatization"
        ],
        "text": "保護施設の犬たちは、まるで生きた展示品のように、来訪者の目にさらされていた。"
    },
    {
        "id": "hypostatization_118",
        "rhetorical_device": [
            "hypostatization"
        ],
        "text": "天文台の望遠鏡は、まるで巨大な金属の目のように夜空を見つめていた。"
    },
    {
        "id": "hypostatization_119",
        "rhetorical_device": [
            "hypostatization"
        ],
        "text": "舞台上の俳優たちは、まるで操り人形のように演出家の意のままに動いていた。"
    },
    {
        "id": "hypostatization_120",
        "rhetorical_device": [
            "hypostatization"
        ],
        "text": "アイスフィッシングの穴から引き上げられた魚は、氷の結晶のように輝いていた。その鱗は凍てつく空気の中で宝石のように光っていた。"
    },
    {
        "id": "hypostatization_121",
        "rhetorical_device": [
            "hypostatization"
        ],
        "text": "彼女の社会貢献への情熱は、暗闇を照らす灯台のビームのように力強く、揺るぎなかった。"
    },
    {
        "id": "hypostatization_122",
        "rhetorical_device": [
            "hypostatization"
        ],
        "text": "その漫画家は、鉛筆を持つと机に根を生やしたかのように動かなくなった。"
    },
    {
        "id": "hypostatization_123",
        "rhetorical_device": [
            "hypostatization"
        ],
        "text": "持続可能な観光を推進する彼の言葉は、鉄のように強く、聴衆の心に響いた。"
    },
    {
        "id": "hypostatization_124",
        "rhetorical_device": [
            "hypostatization"
        ],
        "text": "彼の心は、長年の失恋によって化石化し、もはや愛を受け入れる余地はなかった。"
    },
    {
        "id": "hypostatization_125",
        "rhetorical_device": [
            "hypostatization"
        ],
        "text": "クルーズ船のデッキに立つと、波の音だけが聞こえる。人々はまるで彫刻のように静かに佇み、海の景色に見入っていた。"
    },
    {
        "id": "hypostatization_126",
        "rhetorical_device": [
            "hypostatization"
        ],
        "text": "サイクリングコースを走る彼らの姿は、まるで風に乗る葉のようだった。軽やかに、そして静かに景色の中を滑るように進んでいく。"
    },
    {
        "id": "hypostatization_127",
        "rhetorical_device": [
            "hypostatization"
        ],
        "text": "平等な賃金を求める彼女の声は、硬い岩盤を砕く鉄槌のように力強かった。その言葉が、古い制度の壁を少しずつ崩していった。"
    },
    {
        "id": "hypostatization_128",
        "rhetorical_device": [
            "hypostatization"
        ],
        "text": "山菜採りに夢中になった彼らは、森の中で木の根のように地面に張り付いていた。"
    },
    {
        "id": "hypostatization_129",
        "rhetorical_device": [
            "hypostatization"
        ],
        "text": "ワインテイスティング会で、参加者たちはグラスを手に持ち、まるでワインセラーの中の整然と並んだボトルのように静かに立ち尽くしていた。"
    },
    {
        "id": "hypostatization_130",
        "rhetorical_device": [
            "hypostatization"
        ],
        "text": "フリーランサーとして働き始めて3年、彼女は仕事への情熱を失い、ただの歯車になってしまった気がした。"
    },
    {
        "id": "hypostatization_131",
        "rhetorical_device": [
            "hypostatization"
        ],
        "text": "盆栽の展示会場を歩いていると、何百年もの歴史が凝縮された小宇宙が広がっていた。それぞれの盆栽は、時を閉じ込めた箱庭のようだった。"
    },
    {
        "id": "hypostatization_132",
        "rhetorical_device": [
            "hypostatization"
        ],
        "text": "研修中、彼の脳は情報を吸収するスポンジのようだった。"
    },
    {
        "id": "hypostatization_133",
        "rhetorical_device": [
            "hypostatization"
        ],
        "text": "予防医学の重要性を説く医師の言葉は、鉄の壁のように固く、患者の耳に響いた。"
    },
    {
        "id": "hypostatization_134",
        "rhetorical_device": [
            "hypostatization"
        ],
        "text": "新入社員たちは、企業文化という型枠に流し込まれる生コンクリートのようだった。"
    },
    {
        "id": "hypostatization_135",
        "rhetorical_device": [
            "hypostatization"
        ],
        "text": "クラウドコンピューティングの世界では、データはまるで空気のように、どこにでも存在し、どこにも存在しないかのようだ。"
    },
    {
        "id": "hypostatization_136",
        "rhetorical_device": [
            "hypostatization"
        ],
        "text": "植物性の食材だけで作られたハンバーガーを口に運ぶと、まるで口の中で小さな草原が広がったかのような錯覚に陥った。"
    },
    {
        "id": "hypostatization_137",
        "rhetorical_device": [
            "hypostatization"
        ],
        "text": "長い道のりを走り続けた車は、まるで疲れ果てた戦士のように、ガレージに滑り込んだ。"
    },
    {
        "id": "hypostatization_138",
        "rhetorical_device": [
            "hypostatization"
        ],
        "text": "DIY文化に没頭する彼は、まるで多機能工具のように、どんな状況にも対応できる万能な人間になっていった。"
    },
    {
        "id": "hypostatization_139",
        "rhetorical_device": [
            "hypostatization"
        ],
        "text": "ガラスエッチングの技術を習得するには、レーザーのような集中力が必要だ。"
    },
    {
        "id": "hypostatization_140",
        "rhetorical_device": [
            "hypostatization"
        ],
        "text": "ナノテクノロジーの研究に没頭する彼は、まるで精密機械のように感情を失い、ただデータを処理するだけの存在になっていった。"
    },
    {
        "id": "hypostatization_141",
        "rhetorical_device": [
            "hypostatization"
        ],
        "text": "予防接種を受ける子供たちは、注射器を見た途端に塩の柱になってしまった。"
    },
    {
        "id": "hypostatization_142",
        "rhetorical_device": [
            "hypostatization"
        ],
        "text": "映画館を出た観客たちは、感動で石になったかのように動かなかった。"
    },
    {
        "id": "hypostatization_143",
        "rhetorical_device": [
            "hypostatization"
        ],
        "text": "観光客で賑わう街は、まるで巨大な蟻の巣のようだった。人々は目的地へと忙しなく行き交い、その姿は働き者の蟻そのものだった。"
    },
    {
        "id": "hypostatization_144",
        "rhetorical_device": [
            "hypostatization"
        ],
        "text": "祭りの山車を引く男たちは、まるで巨大な歯車の一部のように、息を合わせて動いていた。"
    },
    {
        "id": "hypostatization_145",
        "rhetorical_device": [
            "hypostatization"
        ],
        "text": "彼の言葉は刃物のように鋭く、相手の心を切り裂いた。それでも、彼の表情は石のように無表情のままだった。"
    },
    {
        "id": "hypostatization_146",
        "rhetorical_device": [
            "hypostatization"
        ],
        "text": "カメラを構えた彼は、岩のように動かず、獲物を待ち構える捕食者さながらだった。"
    },
    {
        "id": "hypostatization_147",
        "rhetorical_device": [
            "hypostatization"
        ],
        "text": "古い映画館の座席に腰掛けた観客たちは、スクリーンに映る映像に魅入られ、まるで彫刻のように動かなかった。"
    },
    {
        "id": "hypostatization_148",
        "rhetorical_device": [
            "hypostatization"
        ],
        "text": "レゴブロックで作られた街並みを見ていると、そこに住む小さな人々の姿が目に浮かぶ。プラスチックの魂が宿ったかのような錯覚に陥る。"
    },
    {
        "id": "hypostatization_149",
        "rhetorical_device": [
            "hypostatization"
        ],
        "text": "新薬の副作用に苦しむ患者たちは、まるで壊れたロボットのように病院の廊下をよろめきながら歩いていた。"
    },
    {
        "id": "hypostatization_150",
        "rhetorical_device": [
            "hypostatization"
        ],
        "text": "気候変動対策に無関心な政治家たちは、まるで氷河のように動きが遅く、変化を受け入れようとしなかった。"
    },
    {
        "id": "hypostatization_151",
        "rhetorical_device": [
            "hypostatization"
        ],
        "text": "彼女の心は、ゴシック小説の古城のように、暗く、冷たく、そして秘密に満ちていた。誰も、その心の扉を開くことができずにいた。"
    },
    {
        "id": "hypostatization_152",
        "rhetorical_device": [
            "hypostatization"
        ],
        "text": "伝統工芸の職人たちは、まるで時が止まったかのように、何世紀もの間同じ姿勢で作業を続けてきた。"
    },
    {
        "id": "hypostatization_153",
        "rhetorical_device": [
            "hypostatization"
        ],
        "text": "人工の珊瑚礁が海底に沈められると、それはまるで海の中の街のように見えた。魚たちはその新しい住処を探検する観光客のようだった。"
    },
    {
        "id": "hypostatization_154",
        "rhetorical_device": [
            "hypostatization"
        ],
        "text": "彼女の心は氷のように冷たく、どんな温かい言葉も溶かすことができなかった。"
    },
    {
        "id": "hypostatization_155",
        "rhetorical_device": [
            "hypostatization"
        ],
        "text": "石鹸職人の腕は、長年の作業で磨き上げられた大理石のように滑らかで堅固だった。"
    },
    {
        "id": "hypostatization_156",
        "rhetorical_device": [
            "hypostatization"
        ],
        "text": "クラフトビールの泡は、まるで雲のように軽やかに立ち昇り、グラスの縁で踊っていた。"
    },
    {
        "id": "hypostatization_157",
        "rhetorical_device": [
            "hypostatization"
        ],
        "text": "AIの進化に伴い、人間の感情はデータベースに格納された情報のように扱われるようになった。"
    },
    {
        "id": "hypostatization_158",
        "rhetorical_device": [
            "hypostatization"
        ],
        "text": "南米の密林を歩いていると、まるで時が止まったかのように、木々は石柱のごとく動かなかった。"
    },
    {
        "id": "hypostatization_159",
        "rhetorical_device": [
            "hypostatization"
        ],
        "text": "都会の農園で働く人々は、コンクリートジャングルに咲いた花のように、周囲の喧騒とは不釣り合いな存在だった。"
    },
    {
        "id": "hypostatization_160",
        "rhetorical_device": [
            "hypostatization"
        ],
        "text": "新入社員たちは、まるでプログラムされたロボットのように、講師の言葉を一言一句聞き逃さないよう必死だった。"
    },
    {
        "id": "hypostatization_161",
        "rhetorical_device": [
            "hypostatization"
        ],
        "text": "深海魚たちは、闇の中で光る宝石のようだった。その姿は、海底の暗闇を彩る生きた装飾品のようでもあった。"
    },
    {
        "id": "hypostatization_162",
        "rhetorical_device": [
            "hypostatization"
        ],
        "text": "彼女の手つきは陶芸の名人そのものだった。まるで粘土が彼女の指の延長であるかのように、器用に形を作り上げていく。"
    },
    {
        "id": "hypostatization_163",
        "rhetorical_device": [
            "hypostatization"
        ],
        "text": "ツアーガイドの声は、まるで歴史という糸で編まれた絨毯のようだった。一つ一つの言葉が、過去の出来事を鮮やかに織り上げていく。"
    },
    {
        "id": "hypostatization_164",
        "rhetorical_device": [
            "hypostatization"
        ],
        "text": "美術館に展示された彫刻は、冷たい金属でできているのに、まるで呼吸しているかのように感じられた。"
    },
    {
        "id": "hypostatization_165",
        "rhetorical_device": [
            "hypostatization"
        ],
        "text": "その彫刻は、まるで石から解放されようとしている魂のようだった。冷たい大理石の中に、生命の鼓動を感じるようだった。"
    },
    {
        "id": "hypostatization_166",
        "rhetorical_device": [
            "hypostatization"
        ],
        "text": "豪華客船の中は、まるで動く都市のようだった。廊下は街路となり、レストランは広場に、客室は小さな家々に見えた。"
    },
    {
        "id": "hypostatization_167",
        "rhetorical_device": [
            "hypostatization"
        ],
        "text": "夕暮れ時の街並みは、まるで時が凍りついたかのように静寂に包まれていた。"
    },
    {
        "id": "hypostatization_168",
        "rhetorical_device": [
            "hypostatization"
        ],
        "text": "彼の心は石のように固く、どんな説得も通用しなかった。"
    },
    {
        "id": "hypostatization_169",
        "rhetorical_device": [
            "hypostatization"
        ],
        "text": "DNAの二重らせん構造は、生命の設計図を記した神秘的な暗号文のように、研究者の前に横たわっていた。"
    },
    {
        "id": "hypostatization_170",
        "rhetorical_device": [
            "hypostatization"
        ],
        "text": "その古い文書は、まるで時を閉じ込めた箱のように、過去の秘密を守り続けていた。"
    },
    {
        "id": "hypostatization_171",
        "rhetorical_device": [
            "hypostatization"
        ],
        "text": "サイクリングに没頭するあまり、彼女の足はペダルの一部と化し、もはや人間の肉体とは思えないほどだった。"
    },
    {
        "id": "hypostatization_172",
        "rhetorical_device": [
            "hypostatization"
        ],
        "text": "暗号技術者たちは、セキュリティの壁を築き上げるため、まるでデジタルの石工のように、コードの要塞を組み上げていった。"
    },
    {
        "id": "hypostatization_173",
        "rhetorical_device": [
            "hypostatization"
        ],
        "text": "新しいガジェットを組み立てる彼女の指は、まるでロボットアームのように正確で効率的に動いていた。"
    },
    {
        "id": "hypostatization_174",
        "rhetorical_device": [
            "hypostatization"
        ],
        "text": "ペットの猫を撮影しようとすると、まるでミサイルのようにカメラから逃げ去っていった。"
    },
    {
        "id": "hypostatization_175",
        "rhetorical_device": [
            "hypostatization"
        ],
        "text": "深海での潜水中、私たちは海底火山の噴出口の周りに集まる生物たちを見て、まるで動かない鉱物の結晶のような光景だと思った。"
    },
    {
        "id": "hypostatization_176",
        "rhetorical_device": [
            "hypostatization"
        ],
        "text": "クラウドサービスの障害で、企業のシステムはまるで砂の城のように脆く崩れ去った。"
    },
    {
        "id": "hypostatization_177",
        "rhetorical_device": [
            "hypostatization"
        ],
        "text": "その会社は巨大な機械のようで、社員たちはただの歯車にすぎなかった。"
    },
    {
        "id": "hypostatization_178",
        "rhetorical_device": [
            "hypostatization"
        ],
        "text": "ジャムの甘い香りが部屋中に広がり、まるで砂糖の城に閉じ込められたかのような錯覚を覚えた。"
    },
    {
        "id": "hypostatization_179",
        "rhetorical_device": [
            "hypostatization"
        ],
        "text": "彼女の筆遣いは、まるで大理石のように冷たく精密だった。現代書道の世界で、彼女の作品は氷の彫刻のように人々の心を凍らせた。"
    },
    {
        "id": "hypostatization_180",
        "rhetorical_device": [
            "hypostatization"
        ],
        "text": "新入社員たちは、キャリアパスという迷路の中で、まるで迷子の駒のように彷徨っていた。"
    },
    {
        "id": "hypostatization_181",
        "rhetorical_device": [
            "hypostatization"
        ],
        "text": "ダンスフロアで彼女は、まるでゴムでできているかのように体を自在に曲げ、観客を魅了した。"
    },
    {
        "id": "hypostatization_182",
        "rhetorical_device": [
            "hypostatization"
        ],
        "text": "AIの倫理問題を議論する会議は、まるで迷路のように複雑で、出口が見えない状況だった。"
    },
    {
        "id": "hypostatization_183",
        "rhetorical_device": [
            "hypostatization"
        ],
        "text": "星空を見上げる彼女の瞳は、夜空そのものの様に深く、輝いていた。"
    },
    {
        "id": "hypostatization_184",
        "rhetorical_device": [
            "hypostatization"
        ],
        "text": "彼の意志は鋼鉄のように固く、どんな困難も曲げることはできなかった。"
    },
    {
        "id": "hypostatization_185",
        "rhetorical_device": [
            "hypostatization"
        ],
        "text": "アーチェリー選手の姿勢は、引き絞られた弓のように緊張感に満ちていた。周囲の空気さえも、彼の集中力に押し潰されそうだった。"
    },
    {
        "id": "hypostatization_186",
        "rhetorical_device": [
            "hypostatization"
        ],
        "text": "彼女の指は針のように素早く、布地を縫い合わせていった。"
    },
    {
        "id": "hypostatization_187",
        "rhetorical_device": [
            "hypostatization"
        ],
        "text": "彼女はダンスセラピーの最中、まるで大理石の彫刻のように静止していた。その姿は、内なる感情の嵐とは対照的だった。"
    },
    {
        "id": "hypostatization_188",
        "rhetorical_device": [
            "hypostatization"
        ],
        "text": "ボランティアリーダーの厳しい指示に、メンバーたちはまるで操り人形のように黙々と従っていた。"
    },
    {
        "id": "hypostatization_189",
        "rhetorical_device": [
            "hypostatization"
        ],
        "text": "デジタルマーケティングの世界では、ビッグデータという巨大な機械の歯車として、消費者が回されているような感覚に陥ることがある。"
    },
    {
        "id": "hypostatization_190",
        "rhetorical_device": [
            "hypostatization"
        ],
        "text": "彼女のスクラップブックは、まるで記憶の倉庫のように、過去の瞬間を整然と保管していた。"
    },
    {
        "id": "hypostatization_191",
        "rhetorical_device": [
            "hypostatization"
        ],
        "text": "サプライズパーティーで、誕生日を祝われた彼女は喜びのあまり、まるでろうそくの炎のように揺らめいていた。"
    },
    {
        "id": "hypostatization_192",
        "rhetorical_device": [
            "hypostatization"
        ],
        "text": "海底の珊瑚礁は、まるで石でできた街のようだった。魚たちはその通りを泳ぎ、海藻は風に揺れる木々のように揺らめいていた。"
    },
    {
        "id": "hypostatization_193",
        "rhetorical_device": [
            "hypostatization"
        ],
        "text": "彼女の不安は、まるで重力のように彼女を地面に引き寄せ、身動きが取れなくなっていた。"
    },
    {
        "id": "hypostatization_194",
        "rhetorical_device": [
            "hypostatization"
        ],
        "text": "長期熟成されたチーズは、まるで賢者のように深い味わいを秘めていた。"
    },
    {
        "id": "hypostatization_195",
        "rhetorical_device": [
            "hypostatization"
        ],
        "text": "バランスを取るのに苦心する岩は、まるで生命を宿したかのように、積み上げる人の意志と対話しているようだった。"
    },
    {
        "id": "hypostatization_196",
        "rhetorical_device": [
            "hypostatization"
        ],
        "text": "ペットの写真展で、犬たちは飼い主の腕の中で、まるでぬいぐるみのように愛らしく、動かずにいた。"
    },
    {
        "id": "hypostatization_197",
        "rhetorical_device": [
            "hypostatization"
        ],
        "text": "その文化は、まるで生きた有機体のように、時代とともに形を変え、成長していった。"
    },
    {
        "id": "hypostatization_198",
        "rhetorical_device": [
            "hypostatization"
        ],
        "text": "舞台上の彼は、まるで操り人形のように、演出家の意図通りに動いていた。"
    },
    {
        "id": "hypostatization_199",
        "rhetorical_device": [
            "hypostatization"
        ],
        "text": "新しい抗うつ薬を服用した患者は、まるで機械の部品に油が差されたかのように、スムーズに日常生活を送れるようになった。"
    },
    {
        "id": "hypostatization_200",
        "rhetorical_device": [
            "hypostatization"
        ],
        "text": "新入社員たちは、まるでロボットのように効率的に働き、上司を驚かせた。"
    },
    {
        "id": "hypostatization_201",
        "rhetorical_device": [
            "hypostatization"
        ],
        "text": "パズルを完成させた後、彼は達成感で満たされ、まるで銅像のように誇らしげに立っていた。"
    },
    {
        "id": "hypostatization_202",
        "rhetorical_device": [
            "hypostatization"
        ],
        "text": "クラフトビールの味は、まるで音楽のように舌の上で奏でられ、五感を刺激した。"
    },
    {
        "id": "hypostatization_203",
        "rhetorical_device": [
            "hypostatization"
        ],
        "text": "彼女の心は氷のように冷たく、どんな熱い言葉も溶かすことができなかった。"
    },
    {
        "id": "hypostatization_204",
        "rhetorical_device": [
            "hypostatization"
        ],
        "text": "洞窟探検に挑戦した彼は、岩のように固い決意を胸に秘めていた。暗闇の中、その決意が彼を導く灯台となった。"
    },
    {
        "id": "hypostatization_205",
        "rhetorical_device": [
            "hypostatization"
        ],
        "text": "市議会の会議室は冷たい空気に包まれていた。議員たちは石のように固く、感情を表に出すことはなかった。"
    },
    {
        "id": "hypostatization_206",
        "rhetorical_device": [
            "hypostatization"
        ],
        "text": "深夜のラジオ番組で、DJの声は静かな夜の闇に溶け込む蝋燭の炎のようだった。リスナーたちは、その温かな光に包まれるように耳を傾けていた。"
    },
    {
        "id": "hypostatization_207",
        "rhetorical_device": [
            "hypostatization"
        ],
        "text": "釣り大会の参加者たちは、まるで湖面に浮かぶ無数の浮きのように、静かに結果を待っていた。"
    },
    {
        "id": "hypostatization_208",
        "rhetorical_device": [
            "hypostatization"
        ],
        "text": "その現代アートの展示会場に足を踏み入れると、まるで無機質な宇宙に迷い込んだかのような錯覚に陥った。"
    },
    {
        "id": "hypostatization_209",
        "rhetorical_device": [
            "hypostatization"
        ],
        "text": "極寒の地で遭難した探検隊は、救助を待つ間、まるで時が止まったかのように動かない氷の彫像と化していた。"
    },
    {
        "id": "hypostatization_210",
        "rhetorical_device": [
            "hypostatization"
        ],
        "text": "新しいインテリアデザインは、まるで氷の彫刻のように冷たく洗練されていた。"
    },
    {
        "id": "hypostatization_211",
        "rhetorical_device": [
            "hypostatization"
        ],
        "text": "金属を叩く職人の腕は、ハンマーのように力強く、リズミカルに動いていた。"
    },
    {
        "id": "hypostatization_212",
        "rhetorical_device": [
            "hypostatization"
        ],
        "text": "有機農法を否定する農家たちは、化学肥料という鎧に身を包んだ無機質な戦士のようだった。"
    },
    {
        "id": "hypostatization_213",
        "rhetorical_device": [
            "hypostatization"
        ],
        "text": "都市の屋上で蜂を育てる彼女の手は、長年の経験で風化した岩のようにごつごつしていたが、その動きは蜜を集める蜂と同じくらい繊細だった。"
    },
    {
        "id": "hypostatization_214",
        "rhetorical_device": [
            "hypostatization"
        ],
        "text": "アルジェーバイオ燃料の研究者たちは、まるで砂漠の中のオアシスのように、エネルギー問題の解決に希望をもたらした。"
    },
    {
        "id": "hypostatization_215",
        "rhetorical_device": [
            "hypostatization"
        ],
        "text": "介護士の手は魔法の杖のようで、その優しい触れ方だけで患者の痛みを和らげることができた。"
    },
    {
        "id": "hypostatization_216",
        "rhetorical_device": [
            "hypostatization"
        ],
        "text": "手芸を始めて数ヶ月、彼の指は針のように鋭く、糸のように繊細になっていった。"
    },
    {
        "id": "hypostatization_217",
        "rhetorical_device": [
            "hypostatization"
        ],
        "text": "彼女の心は、ヨーグルトの発酵槽のように静かに熱を帯びていった。"
    },
    {
        "id": "hypostatization_218",
        "rhetorical_device": [
            "hypostatization"
        ],
        "text": "太陽光パネルを見つめる彼女の目は、エネルギーを吸収する光電池のように輝いていた。環境への情熱が、その瞳に宿っているようだった。"
    },
    {
        "id": "hypostatization_219",
        "rhetorical_device": [
            "hypostatization"
        ],
        "text": "ペット写真のコンテストで、審査員たちは鷹の目で各エントリーを吟味していった。"
    },
    {
        "id": "hypostatization_220",
        "rhetorical_device": [
            "hypostatization"
        ],
        "text": "AIの倫理問題を議論する会議室は、まるで巨大なコンピューターの内部のように冷たく無機質だった。"
    },
    {
        "id": "hypostatization_221",
        "rhetorical_device": [
            "hypostatization"
        ],
        "text": "宇宙飛行士たちは、無重力空間で浮遊しながら、まるで宇宙の塵のように静かに漂っていた。"
    },
    {
        "id": "hypostatization_222",
        "rhetorical_device": [
            "hypostatization"
        ],
        "text": "仕事に追われる日々で、彼女の目は窓ガラスのように虚ろになっていった。"
    },
    {
        "id": "hypostatization_223",
        "rhetorical_device": [
            "hypostatization"
        ],
        "text": "誕生日ケーキを前に、子供たちはまるでロウソクの炎のように、目を輝かせていた。"
    },
    {
        "id": "hypostatization_224",
        "rhetorical_device": [
            "hypostatization"
        ],
        "text": "誕生日パーティーの準備に追われる母親は、まるでゼンマイ仕掛けの人形のように、休む間もなく動き回っていた。"
    },
    {
        "id": "hypostatization_225",
        "rhetorical_device": [
            "hypostatization"
        ],
        "text": "新人バンドのメンバーたちは、プロデューサーの手によって粘土のように形作られていった。"
    },
    {
        "id": "hypostatization_226",
        "rhetorical_device": [
            "hypostatization"
        ],
        "text": "CSR活動に取り組む企業は、社会の歯車として重要な役割を果たしている。"
    },
    {
        "id": "hypostatization_227",
        "rhetorical_device": [
            "hypostatization"
        ],
        "text": "ロッククライミングの初心者たちは、岩壁にしがみつく木の根のように必死だった。"
    },
    {
        "id": "hypostatization_228",
        "rhetorical_device": [
            "hypostatization"
        ],
        "text": "海底に沈む遺跡を前に、考古学者たちは石像のように動かなかった。何世紀もの時を越えて、過去の秘密が彼らの前に横たわっていた。"
    },
    {
        "id": "hypostatization_229",
        "rhetorical_device": [
            "hypostatization"
        ],
        "text": "タトゥーを入れた瞬間、彼の皮膚は生きたキャンバスに変わり、色とりどりの物語を語り始めた。"
    },
    {
        "id": "hypostatization_230",
        "rhetorical_device": [
            "hypostatization"
        ],
        "text": "多様性を尊重するはずの会議で、少数派の意見は砂粒のようにかき消されていった。"
    },
    {
        "id": "hypostatization_231",
        "rhetorical_device": [
            "hypostatization"
        ],
        "text": "パズルのピースを探す彼の目は、レーザーのように鋭く、部屋中を走り回っていた。"
    },
    {
        "id": "hypostatization_232",
        "rhetorical_device": [
            "hypostatization"
        ],
        "text": "緑茶の味わいは、まるで森林のように深く、山のように力強かった。"
    },
    {
        "id": "hypostatization_233",
        "rhetorical_device": [
            "hypostatization"
        ],
        "text": "社会起業家たちは、硬い岩盤に穴を開けるドリルのように、社会の課題に立ち向かっていた。"
    },
    {
        "id": "hypostatization_234",
        "rhetorical_device": [
            "hypostatization"
        ],
        "text": "彼女は紅茶の味わいについて語るとき、まるで詩人のように言葉が花開いた。"
    },
    {
        "id": "hypostatization_235",
        "rhetorical_device": [
            "hypostatization"
        ],
        "text": "天体写真家たちは、夜空という広大なキャンバスに、星々を絵の具のように塗り重ねていく。"
    },
    {
        "id": "hypostatization_236",
        "rhetorical_device": [
            "hypostatization"
        ],
        "text": "彼女は有機農業に情熱を注ぐあまり、畑の中で土と一体化したかのように動かなくなった。"
    },
    {
        "id": "hypostatization_237",
        "rhetorical_device": [
            "hypostatization"
        ],
        "text": "気候変動の影響で、かつて生命力に満ちていた森林が今では石のように冷たく、生気を失っていた。"
    },
    {
        "id": "hypostatization_238",
        "rhetorical_device": [
            "hypostatization"
        ],
        "text": "データセンターの中を歩く管理者は、まるでコンピューターのCPUのように冷静に判断を下していった。"
    },
    {
        "id": "hypostatization_239",
        "rhetorical_device": [
            "hypostatization"
        ],
        "text": "医療システムの改革に取り組む政治家たちは、まるで巨大な機械の歯車のように、複雑に絡み合っていた。"
    },
    {
        "id": "hypostatization_240",
        "rhetorical_device": [
            "hypostatization"
        ],
        "text": "遺伝子操作された植物たちは、まるで生きたコンピュータープログラムのように、整然と並んでいた。"
    },
    {
        "id": "hypostatization_241",
        "rhetorical_device": [
            "hypostatization"
        ],
        "text": "ベテラン釣り師の手には、長年の経験が刻まれた樹皮のようなしわが刻まれていた。"
    },
    {
        "id": "hypostatization_242",
        "rhetorical_device": [
            "hypostatization"
        ],
        "text": "アドベンチャーレースの参加者たちは、まるでゼンマイ仕掛けの人形のように、疲れを見せずに走り続けた。"
    },
    {
        "id": "hypostatization_243",
        "rhetorical_device": [
            "hypostatization"
        ],
        "text": "町議会の選挙戦は熾烈を極めた。候補者たちは政治という盤上で、まるでチェスの駒のように動かされ、時に捨て駒となっていった。"
    },
    {
        "id": "hypostatization_244",
        "rhetorical_device": [
            "hypostatization"
        ],
        "text": "タトゥーアーティストの手は、まるで機械のように正確で、肌の上を滑るように動いていった。"
    },
    {
        "id": "hypostatization_245",
        "rhetorical_device": [
            "hypostatization"
        ],
        "text": "殺人事件の容疑者は、取り調べ室で人間性を失った人形のように無表情に座っていた。"
    },
    {
        "id": "hypostatization_246",
        "rhetorical_device": [
            "hypostatization"
        ],
        "text": "会社の中間管理職は、上層部の意向を伝える歯車のような存在だった。"
    },
    {
        "id": "hypostatization_247",
        "rhetorical_device": [
            "hypostatization"
        ],
        "text": "倫理委員会の面々は、AIの是非を議論する中で、まるで石像のように動かぬ表情を浮かべていた。"
    },
    {
        "id": "hypostatization_248",
        "rhetorical_device": [
            "hypostatization"
        ],
        "text": "キャリアコーチの言葉は、まるで鉄の壁のように冷たく、私の心に響かなかった。"
    },
    {
        "id": "hypostatization_249",
        "rhetorical_device": [
            "hypostatization"
        ],
        "text": "カメラのシャッター音が鳴り響く中、モデルは一糸乱れぬポーズを保っていた。まるで大理石の彫像のように美しく、冷たさすら感じられた。"
    },
    {
        "id": "hypostatization_250",
        "rhetorical_device": [
            "hypostatization"
        ],
        "text": "多様性を重んじる会社でさえ、時として氷のような冷たさで新しいアイデアを拒絶することがあった。"
    },
    {
        "id": "hypostatization_251",
        "rhetorical_device": [
            "hypostatization"
        ],
        "text": "人形作りに没頭する彼女の指は、まるで精密機械のように正確に動いていた。"
    },
    {
        "id": "hypostatization_252",
        "rhetorical_device": [
            "hypostatization"
        ],
        "text": "彼女は、まるで完璧に刈り込まれた盆栽のように、感情を表に出さなかった。"
    },
    {
        "id": "hypostatization_253",
        "rhetorical_device": [
            "hypostatization"
        ],
        "text": "paranormal investigationの現場で、彼は恐怖で氷の彫刻のように凍りついていた。"
    },
    {
        "id": "hypostatization_254",
        "rhetorical_device": [
            "hypostatization"
        ],
        "text": "健康診断の結果を待つ間、彼女は不安で机に釘付けになっていた。"
    },
    {
        "id": "hypostatization_255",
        "rhetorical_device": [
            "hypostatization"
        ],
        "text": "再生可能エネルギーの議論は、まるで根を張る大樹のように、社会に深く浸透していった。"
    },
    {
        "id": "hypostatization_256",
        "rhetorical_device": [
            "hypostatization"
        ],
        "text": "彼女は茶葉を選ぶとき、まるで磁石のように最高品質のものに引き寄せられていった。"
    },
    {
        "id": "hypostatization_257",
        "rhetorical_device": [
            "hypostatization"
        ],
        "text": "無線機の前に座る彼は、まるで灯台のように、遠くからの信号を待ち続けていた。"
    },
    {
        "id": "hypostatization_258",
        "rhetorical_device": [
            "hypostatization"
        ],
        "text": "歴史的建造物の保存に反対する人々は、まるで石でできた心を持っているかのようだった。"
    },
    {
        "id": "hypostatization_259",
        "rhetorical_device": [
            "hypostatization"
        ],
        "text": "労働者の権利を無視する経営陣は、まるで鉄の心臓を持っているかのようだった。"
    },
    {
        "id": "hypostatization_260",
        "rhetorical_device": [
            "hypostatization"
        ],
        "text": "仕事に追われる毎日で、彼の心は機械のように冷たくなっていった。"
    },
    {
        "id": "hypostatization_261",
        "rhetorical_device": [
            "hypostatization"
        ],
        "text": "オーストラリアのアウトバックで迷子になった観光客は、砂漠の風景に溶け込み、ほとんど岩のような存在になっていた。"
    },
    {
        "id": "hypostatization_262",
        "rhetorical_device": [
            "hypostatization"
        ],
        "text": "在宅介護を受ける老人たちは、まるで時間が止まった砂時計のようだった。"
    },
    {
        "id": "hypostatization_263",
        "rhetorical_device": [
            "hypostatization"
        ],
        "text": "若い陶芸家の手は、まるで粘土と一体化した道具のように、器を形作っていった。"
    },
    {
        "id": "hypostatization_264",
        "rhetorical_device": [
            "hypostatization"
        ],
        "text": "フェアトレードの認証を受けた農園は、正義の灯台のように輝いていた。"
    },
    {
        "id": "hypostatization_265",
        "rhetorical_device": [
            "hypostatization"
        ],
        "text": "暗号解読に没頭する彼女の目は、コンピューターの画面に映る数字の海に溶け込み、まるでデジタルの一部となったかのようだった。"
    },
    {
        "id": "hypostatization_266",
        "rhetorical_device": [
            "hypostatization"
        ],
        "text": "水耕栽培システムのポンプは、まるで植物の心臓のように、絶え間なく養分を送り続けていた。"
    },
    {
        "id": "hypostatization_267",
        "rhetorical_device": [
            "hypostatization"
        ],
        "text": "クライアントの要求に応えようと必死になるフリーランサーたちは、まるでゼンマイ仕掛けのおもちゃのように働き続けた。"
    },
    {
        "id": "hypostatization_268",
        "rhetorical_device": [
            "hypostatization"
        ],
        "text": "インクルージョンの会議で、彼女の意見は岩のように固く、誰も動かすことができなかった。"
    },
    {
        "id": "hypostatization_269",
        "rhetorical_device": [
            "hypostatization"
        ],
        "text": "彼女の診断結果を聞いた瞬間、私の体は氷の彫刻のように凍りついた。動くことも、言葉を発することもできなかった。"
    },
    {
        "id": "hypostatization_270",
        "rhetorical_device": [
            "hypostatization"
        ],
        "text": "ナノスケールの世界を研究する科学者たちは、まるで顕微鏡の一部となり、微小な粒子と同化していくかのようだった。"
    },
    {
        "id": "hypostatization_271",
        "rhetorical_device": [
            "hypostatization"
        ],
        "text": "その民族学者は、まるで人間の図書館のように、様々な文化の知識を蓄えていた。"
    },
    {
        "id": "hypostatization_272",
        "rhetorical_device": [
            "hypostatization"
        ],
        "text": "彼女の言葉は刃物のように鋭く、相手の心を深く傷つけた。"
    },
    {
        "id": "hypostatization_273",
        "rhetorical_device": [
            "hypostatization"
        ],
        "text": "伝統的な着物を着た彼女は、まるで美術館の展示品のように動きを制限され、優雅に歩いていた。"
    },
    {
        "id": "hypostatization_274",
        "rhetorical_device": [
            "hypostatization"
        ],
        "text": "ダンサーたちは、まるで風に乗って舞う花びらのように、舞台を軽やかに舞った。"
    },
    {
        "id": "hypostatization_275",
        "rhetorical_device": [
            "hypostatization"
        ],
        "text": "タトゥーを入れた瞬間、彼の皮膚は絵画のキャンバスに変わり、感情のない色彩が広がっていった。"
    },
    {
        "id": "hypostatization_276",
        "rhetorical_device": [
            "hypostatization"
        ],
        "text": "バレエダンサーたちは、舞台上で風に揺れる花びらのように優雅に動いていた。しかし、その背後には鋼鉄のような強靭な筋肉と意志が隠されていた。"
    },
    {
        "id": "hypostatization_277",
        "rhetorical_device": [
            "hypostatization"
        ],
        "text": "山頂で朝日を待つ写真家たちは、まるで岩肌から生えた木々のように、動かずにそこに立っていた。"
    },
    {
        "id": "hypostatization_278",
        "rhetorical_device": [
            "hypostatization"
        ],
        "text": "映画館を出た観客たちは、感動で溶けたキャンドルのようにぐったりとしていた。"
    },
    {
        "id": "hypostatization_279",
        "rhetorical_device": [
            "hypostatization"
        ],
        "text": "ヨーグルト作りに没頭する彼女の目は、発酵中の乳酸菌のように生き生きと輝いていた。"
    },
    {
        "id": "hypostatization_280",
        "rhetorical_device": [
            "hypostatization"
        ],
        "text": "手作りのドレスを着た彼女は、まるで花瓶から抜け出してきた花のように会場で輝いていた。"
    },
    {
        "id": "hypostatization_281",
        "rhetorical_device": [
            "hypostatization"
        ],
        "text": "持続可能な観光地として有名になった村は、まるで時計の歯車のように、すべてが完璧に噛み合っていた。"
    },
    {
        "id": "hypostatization_282",
        "rhetorical_device": [
            "hypostatization"
        ],
        "text": "彼女の笑顔は、まるで氷のように冷たく、観客の心を凍らせた。そのスタンドアップコメディアンは、ジョークを言うたびに、会場の空気が固まっていくのを感じた。"
    },
    {
        "id": "hypostatization_283",
        "rhetorical_device": [
            "hypostatization"
        ],
        "text": "釣り大会で優勝した瞬間、彼の体は喜びで震えるはずだったのに、まるで石像のように動かなかった。"
    },
    {
        "id": "hypostatization_284",
        "rhetorical_device": [
            "hypostatization"
        ],
        "text": "性的マイノリティの人々は、社会の中で透明な存在として扱われ、その声は壁に吸い込まれていった。"
    },
    {
        "id": "hypostatization_285",
        "rhetorical_device": [
            "hypostatization"
        ],
        "text": "堆肥置き場から立ち上る蒸気は、地球の呼吸のようにゆっくりと空に溶けていった。"
    },
    {
        "id": "hypostatization_286",
        "rhetorical_device": [
            "hypostatization"
        ],
        "text": "熟練の釣り師は、岩のように動かない忍耐力で、魚が餌に食いつくのを待ち続けた。"
    },
    {
        "id": "hypostatization_287",
        "rhetorical_device": [
            "hypostatization"
        ],
        "text": "その研究者たちは、遺伝子を操る神々のようだった。彼らの手にかかれば、生命の設計図さえも書き換えられてしまう。"
    },
    {
        "id": "hypostatization_288",
        "rhetorical_device": [
            "hypostatization"
        ],
        "text": "彼女の縫い目は、まるで鋼鉄の糸で織られたかのように強固だった。"
    },
    {
        "id": "hypostatization_289",
        "rhetorical_device": [
            "hypostatization"
        ],
        "text": "クィディッチの試合中、ビーターたちは人間バットと化し、ブラッジャーを打ち返していた。"
    },
    {
        "id": "hypostatization_290",
        "rhetorical_device": [
            "hypostatization"
        ],
        "text": "ゲームの世界では、プレイヤーたちは駒のように操られ、画面の向こうで無機質に動き回っていた。彼らの感情は、プログラムされたアルゴリズムのように予測可能だった。"
    },
    {
        "id": "hypostatization_291",
        "rhetorical_device": [
            "hypostatization"
        ],
        "text": "彼の心は、長年の失望によって鋼鉄のように冷たく硬くなっていた。"
    },
    {
        "id": "hypostatization_292",
        "rhetorical_device": [
            "hypostatization"
        ],
        "text": "自転車レースの選手たちは、まるで風を切り裂く矢のようだった。空気抵抗さえも無視するかのように、猛スピードで駆け抜けていく。"
    },
    {
        "id": "hypostatization_293",
        "rhetorical_device": [
            "hypostatization"
        ],
        "text": "火事現場で、煙に包まれた建物は、まるで怒りに燃える巨人のように立ちはだかっていた。"
    },
    {
        "id": "hypostatization_294",
        "rhetorical_device": [
            "hypostatization"
        ],
        "text": "熟練のトラッカーは、獲物の痕跡を読み取る時、まるでコンピューターのように正確だった。"
    },
    {
        "id": "hypostatization_295",
        "rhetorical_device": [
            "hypostatization"
        ],
        "text": "観光客たちは、まるで蜂の群れのように、有名な観光地を飛び回っていた。カメラのフラッシュが、花の蜜を求める蜂の羽音のように絶え間なく鳴り響いていた。"
    },
    {
        "id": "hypostatization_296",
        "rhetorical_device": [
            "hypostatization"
        ],
        "text": "簡単レシピを見つけた瞬間、彼女の目は宝石のように輝いた。"
    },
    {
        "id": "hypostatization_297",
        "rhetorical_device": [
            "hypostatization"
        ],
        "text": "新しい公共政策が発表されると、市民たちは将棋の駒のように、政治家の思惑に従って動かされる運命にあった。"
    },
    {
        "id": "hypostatization_298",
        "rhetorical_device": [
            "hypostatization"
        ],
        "text": "彼女の言葉は氷のように冷たく、相手の心を凍らせた。"
    },
    {
        "id": "hypostatization_299",
        "rhetorical_device": [
            "hypostatization"
        ],
        "text": "渋滞に巻き込まれた車列は、まるで動かない岩のようだった。"
    },
    {
        "id": "hypostatization_300",
        "rhetorical_device": [
            "hypostatization"
        ],
        "text": "発酵食品を作る過程で、微生物たちは静かな職人のように黙々と働いていた。"
    },
    {
        "id": "hypostatization_301",
        "rhetorical_device": [
            "hypostatization"
        ],
        "text": "人類学者たちは、古代の遺跡を前に石像のように立ち尽くしていた。"
    },
    {
        "id": "hypostatization_302",
        "rhetorical_device": [
            "hypostatization"
        ],
        "text": "その建築家は、まるでコンピューターのように正確に計算し、設計を進めていった。"
    },
    {
        "id": "hypostatization_303",
        "rhetorical_device": [
            "hypostatization"
        ],
        "text": "ガラスのモザイクアートは、光を浴びると宝石のように輝き、部屋全体を魔法の空間に変えた。"
    },
    {
        "id": "hypostatization_304",
        "rhetorical_device": [
            "hypostatization"
        ],
        "text": "彼の心は、長年の孤独によって、まるで氷の塊のように冷たくなっていた。"
    },
    {
        "id": "hypostatization_305",
        "rhetorical_device": [
            "hypostatization"
        ],
        "text": "クラウドサーバーの前に立つエンジニアは、まるで石柱のように動かなかった。"
    },
    {
        "id": "hypostatization_306",
        "rhetorical_device": [
            "hypostatization"
        ],
        "text": "最新トレンドを追いかける若者たちは、まるで風見鶏のように、流行の風向きに敏感に反応していた。"
    },
    {
        "id": "hypostatization_307",
        "rhetorical_device": [
            "hypostatization"
        ],
        "text": "彼女は舞台に立つと、まるで大理石の彫像のように動きを止めた。観客の息遣いさえ聞こえるほどの静寂が訪れた。"
    },
    {
        "id": "hypostatization_308",
        "rhetorical_device": [
            "hypostatization"
        ],
        "text": "ソムリエの厳しい試験に挑む彼女の姿は、まるでワインセラーの中で何年も熟成されてきたボトルのように落ち着いていた。"
    },
    {
        "id": "hypostatization_309",
        "rhetorical_device": [
            "hypostatization"
        ],
        "text": "凍った湖面に穴を開ける釣り人たちは、まるで氷の彫刻家のようだった。"
    },
    {
        "id": "hypostatization_310",
        "rhetorical_device": [
            "hypostatization"
        ],
        "text": "音楽フェスの観客は、波のように揺れ動いていた。ステージからの音が潮のように押し寄せるたびに、人の海が大きく揺れた。"
    },
    {
        "id": "hypostatization_311",
        "rhetorical_device": [
            "hypostatization"
        ],
        "text": "彼の心は鋼鉄のように強く、どんな感情も跳ね返した。恋人の涙さえ、テフロン加工のフライパンから水が滑り落ちるように、彼の心に染み込まなかった。"
    },
    {
        "id": "hypostatization_312",
        "rhetorical_device": [
            "hypostatization"
        ],
        "text": "タトゥーアーティストの手は、まるで精密機械のように正確に動き、肌という画布に芸術を刻み込んでいった。"
    },
    {
        "id": "hypostatization_313",
        "rhetorical_device": [
            "hypostatization"
        ],
        "text": "盆栽の剪定に没頭するうち、彼の目は顕微鏡のようになり、葉一枚一枚の変化を見逃さなくなった。"
    },
    {
        "id": "hypostatization_314",
        "rhetorical_device": [
            "hypostatization"
        ],
        "text": "彼女の笑顔は、美術館に展示された現代彫刻のように、謎めいて解読不能だった。"
    },
    {
        "id": "hypostatization_315",
        "rhetorical_device": [
            "hypostatization"
        ],
        "text": "灼熱のサバンナを走るランナーたちは、まるで太陽に追われる影のように、黙々と前へ進んでいった。"
    },
    {
        "id": "hypostatization_316",
        "rhetorical_device": [
            "hypostatization"
        ],
        "text": "バレエダンサーたちは、まるで精巧な時計の歯車のように、完璧に同調して動いていた。"
    },
    {
        "id": "hypostatization_317",
        "rhetorical_device": [
            "hypostatization"
        ],
        "text": "DIYファッションショーで、モデルたちはまるでマネキンのように完璧な姿勢を保っていた。"
    },
    {
        "id": "hypostatization_318",
        "rhetorical_device": [
            "hypostatization"
        ],
        "text": "クリスマスツリーの飾り付けに没頭する父は、まるでおもちゃの兵隊のように機械的に動き、黙々と作業を続けた。"
    },
    {
        "id": "hypostatization_319",
        "rhetorical_device": [
            "hypostatization"
        ],
        "text": "彼の笑顔は、ネオンサインのように明るく輝いていたが、その目は曇りガラスのように何も映さなかった。人々は、まるでショーウィンドウの中のマネキンを見るように、彼を眺めていた。"
    },
    {
        "id": "hypostatization_320",
        "rhetorical_device": [
            "hypostatization"
        ],
        "text": "彼のブログ記事は、インターネットの海に浮かぶ灯台のようだった。読者を正しい方向へと導く、不動の存在だった。"
    },
    {
        "id": "hypostatization_321",
        "rhetorical_device": [
            "hypostatization"
        ],
        "text": "釣り大会で優勝を逃した彼は、まるで氷の彫刻のように冷たい表情を浮かべていた。"
    },
    {
        "id": "hypostatization_322",
        "rhetorical_device": [
            "hypostatization"
        ],
        "text": "AIの倫理問題について議論する彼らの表情は、まるでプログラムされたロボットのように無機質だった。"
    },
    {
        "id": "hypostatization_323",
        "rhetorical_device": [
            "hypostatization"
        ],
        "text": "剥製師の手にかかると、かつて生き生きとしていた動物たちは永遠の静寂の中に閉じ込められた彫像と化した。"
    },
    {
        "id": "hypostatization_324",
        "rhetorical_device": [
            "hypostatization"
        ],
        "text": "カメラのシャッター音が鳴る瞬間、野生動物たちは彫像のように静止し、息をひそめた。"
    },
    {
        "id": "hypostatization_325",
        "rhetorical_device": [
            "hypostatization"
        ],
        "text": "その部族の長老たちは、まるで古い樫の木のように、何世紀もの知恵を身にまとっているようだった。"
    },
    {
        "id": "hypostatization_326",
        "rhetorical_device": [
            "hypostatization"
        ],
        "text": "地域経済は氷のように冷え切っていた。新しい産業の種が芽吹くのを待つしかない。"
    },
    {
        "id": "hypostatization_327",
        "rhetorical_device": [
            "hypostatization"
        ],
        "text": "コミュニティガーデンの参加者たちは、日々の雑務に追われ、人間というより歯車のように動いているように見えた。"
    },
    {
        "id": "hypostatization_328",
        "rhetorical_device": [
            "hypostatization"
        ],
        "text": "祭りの屋台に並ぶ人々は、まるで整然と並べられたドミノのようだった。一人が動けば、連鎖反応で全体が動き出す。"
    },
    {
        "id": "hypostatization_329",
        "rhetorical_device": [
            "hypostatization"
        ],
        "text": "社会の歯車として働き続ける彼は、いつしか自分の夢を忘れてしまっていた。"
    },
    {
        "id": "hypostatization_330",
        "rhetorical_device": [
            "hypostatization"
        ],
        "text": "対立する二人の間に立った調停者は、まるで人間の盾のようだった。感情の嵐の中で、冷静さを失わない姿は砦のように見えた。"
    },
    {
        "id": "hypostatization_331",
        "rhetorical_device": [
            "hypostatization"
        ],
        "text": "的を狙う彼女の目は、鋭い矢じりのように輝いていた。周りの喧騒も、彼女の集中力を乱すことはできなかった。"
    },
    {
        "id": "hypostatization_332",
        "rhetorical_device": [
            "hypostatization"
        ],
        "text": "植物園の温室に入ると、まるで時が止まったかのように静寂が支配していた。観葉植物たちは緑の彫刻のごとく、微動だにしなかった。"
    },
    {
        "id": "hypostatization_333",
        "rhetorical_device": [
            "hypostatization"
        ],
        "text": "舞台上の俳優たちは、感情の嵐に翻弄されながらも、まるで操り人形のように演出家の指示に従った。"
    },
    {
        "id": "hypostatization_334",
        "rhetorical_device": [
            "hypostatization"
        ],
        "text": "新しい医療機器を前に、ベテラン医師たちは石像のように動かなかった。変化を受け入れられないのだ。"
    },
    {
        "id": "hypostatization_335",
        "rhetorical_device": [
            "hypostatization"
        ],
        "text": "街路樹は、都会の喧騒の中で、まるで緑の肺のように、新鮮な空気を生み出し続けていた。"
    },
    {
        "id": "hypostatization_336",
        "rhetorical_device": [
            "hypostatization"
        ],
        "text": "紅茶を淹れる際、茶葉は湯の中で花のように開き、香りは部屋中に霧のように広がった。"
    },
    {
        "id": "hypostatization_337",
        "rhetorical_device": [
            "hypostatization"
        ],
        "text": "公衆衛生の専門家たちは、感染症と戦う最前線で、まるで鋼鉄の壁のように立ちはだかっていた。"
    },
    {
        "id": "hypostatization_338",
        "rhetorical_device": [
            "hypostatization"
        ],
        "text": "彼女は茶道の世界に入り込むと、まるで磁器の茶碗のように静かで繊細になった。"
    },
    {
        "id": "hypostatization_339",
        "rhetorical_device": [
            "hypostatization"
        ],
        "text": "色とりどりのガラス片を並べる彼の手は、蜘蛛の糸のように繊細で、しなやかだった。"
    },
    {
        "id": "hypostatization_340",
        "rhetorical_device": [
            "hypostatization"
        ],
        "text": "彼女は写真を撮る瞬間、まるで岩のように静止し、シャッターチャンスを待ち構えた。"
    },
    {
        "id": "hypostatization_341",
        "rhetorical_device": [
            "hypostatization"
        ],
        "text": "ミツバチの保護活動は、花粉のように少しずつ広がり、やがて大きな変化をもたらすだろう。"
    },
    {
        "id": "hypostatization_342",
        "rhetorical_device": [
            "hypostatization"
        ],
        "text": "複雑なデータを目の前にして、彼女の頭脳は精密な機械のように回転し、パターンを見出していった。"
    },
    {
        "id": "hypostatization_343",
        "rhetorical_device": [
            "hypostatization"
        ],
        "text": "性別による差別は、まるで目に見えない鎖のように、彼女の可能性を縛り付けていた。"
    },
    {
        "id": "hypostatization_344",
        "rhetorical_device": [
            "hypostatization"
        ],
        "text": "革新的なアイデアは、会議室の空気を電気のように震わせた。"
    },
    {
        "id": "hypostatization_345",
        "rhetorical_device": [
            "hypostatization"
        ],
        "text": "公正な取引を求める農家たちの声は、遠くから聞こえる雷鳴のようだった。"
    },
    {
        "id": "hypostatization_346",
        "rhetorical_device": [
            "hypostatization"
        ],
        "text": "海底調査船の中で、研究員たちは缶詰の魚のように窮屈そうに身を寄せ合っていた。しかし、その目は新たな発見への期待に輝いていた。"
    },
    {
        "id": "hypostatization_347",
        "rhetorical_device": [
            "hypostatization"
        ],
        "text": "その漫画のキャラクターは、感情を表現する際にまるでロボットのように不自然だった。"
    },
    {
        "id": "hypostatization_348",
        "rhetorical_device": [
            "hypostatization"
        ],
        "text": "天体望遠鏡を覗き込む天文学者の目は、まるで宇宙という海に浮かぶ灯台のようだった。未知の星々を照らし出す、知識の光を放っている。"
    },
    {
        "id": "hypostatization_349",
        "rhetorical_device": [
            "hypostatization"
        ],
        "text": "ヨーグルトを作る過程で、牛乳は少しずつ固まり、まるで大理石のように滑らかな質感に変化していった。"
    },
    {
        "id": "hypostatization_350",
        "rhetorical_device": [
            "hypostatization"
        ],
        "text": "風力発電の巨大な風車は、まるで現代の巨人が地平線上で腕を回しているかのようだった。"
    },
    {
        "id": "hypostatization_351",
        "rhetorical_device": [
            "hypostatization"
        ],
        "text": "サーフボードを削る職人の目は、レーザーのように鋭く素材を見つめていた。"
    },
    {
        "id": "hypostatization_352",
        "rhetorical_device": [
            "hypostatization"
        ],
        "text": "ジオキャッシングに夢中になった彼は、まるでコンパスの針のように、常に北を向いているようだった。"
    },
    {
        "id": "hypostatization_353",
        "rhetorical_device": [
            "hypostatization"
        ],
        "text": "宝石職人の目は顕微鏡のように鋭く、ダイヤモンドの最小の欠陥も見逃さなかった。"
    },
    {
        "id": "hypostatization_354",
        "rhetorical_device": [
            "hypostatization"
        ],
        "text": "彼女のダンスは、まるで風に揺れる柳のようだった。体が風を感じ、自然と共鳴しているかのように、しなやかに動いていた。"
    },
    {
        "id": "hypostatization_355",
        "rhetorical_device": [
            "hypostatization"
        ],
        "text": "エコツーリズムに参加する旅行者たちは、自然の中で岩のように静かに佇み、周囲の環境に溶け込んでいった。"
    },
    {
        "id": "hypostatization_356",
        "rhetorical_device": [
            "hypostatization"
        ],
        "text": "スケートボード大会で転倒した選手は、地面に根付いた木のようにしばらく動けなかった。"
    },
    {
        "id": "hypostatization_357",
        "rhetorical_device": [
            "hypostatization"
        ],
        "text": "彼女は実験室で無言のまま立ち尽くし、まるで白衣を着た彫像のようだった。"
    },
    {
        "id": "hypostatization_358",
        "rhetorical_device": [
            "hypostatization"
        ],
        "text": "彼女の言葉は、まるで鋭い刃物のように相手の心を切り裂いた。"
    },
    {
        "id": "hypostatization_359",
        "rhetorical_device": [
            "hypostatization"
        ],
        "text": "密猟者たちは、象牙という宝石を採掘するかのように、象を次々と倒していった。"
    },
    {
        "id": "hypostatization_360",
        "rhetorical_device": [
            "hypostatization"
        ],
        "text": "議場で演説する政治家の言葉は、レコードの針が引っかかったように同じフレーズを繰り返していた。その主張は、まるでプラスチック製の花のように、生気がなかった。"
    },
    {
        "id": "hypostatization_361",
        "rhetorical_device": [
            "hypostatization"
        ],
        "text": "ゴシック文学の世界は、まるで霧のように濃密で、読者の心を包み込んだ。その物語の中で、登場人物たちは、まるで影のように、現実と幻想の境界線上をさまよっていた。"
    },
    {
        "id": "hypostatization_362",
        "rhetorical_device": [
            "hypostatization"
        ],
        "text": "自己改善の道を歩む彼は、過去の失敗や後悔を、まるで重い鎖のように引きずりながら、前に進もうとしていた。"
    },
    {
        "id": "hypostatization_363",
        "rhetorical_device": [
            "hypostatization"
        ],
        "text": "火星探査機から送られてきた画像を見つめる科学者たちの目は、まるでレンズのように鋭く、未知の生命の痕跡を探していた。"
    },
    {
        "id": "hypostatization_364",
        "rhetorical_device": [
            "hypostatization"
        ],
        "text": "企業研修で失敗した社員たちは、まるでチェスの駒のように次々と降格されていった。"
    },
    {
        "id": "hypostatization_365",
        "rhetorical_device": [
            "hypostatization"
        ],
        "text": "盆栽の枝を剪定する彼の手は、まるで精密機械のように正確で冷たかった。"
    },
    {
        "id": "hypostatization_366",
        "rhetorical_device": [
            "hypostatization"
        ],
        "text": "彼の表情は仮面のように固く、どんな感情も読み取ることができなかった。"
    },
    {
        "id": "hypostatization_367",
        "rhetorical_device": [
            "hypostatization"
        ],
        "text": "給与格差に怒りを感じた彼女は、正義の剣となって会社に立ち向かった。その姿は、まさに鋼鉄の意志を持つ戦士のようだった。"
    },
    {
        "id": "hypostatization_368",
        "rhetorical_device": [
            "hypostatization"
        ],
        "text": "陶芸家の手は、長年の経験で磨かれた道具のようだった。粘土を触れば、まるで魔法の杖のように、素晴らしい形を生み出した。"
    },
    {
        "id": "hypostatization_369",
        "rhetorical_device": [
            "hypostatization"
        ],
        "text": "猫のモデルは、カメラの前で完璧な彫像のようにポーズを取り続けた。その毛並みは、まるで上質な絹のようにしなやかに光を反射していた。"
    },
    {
        "id": "hypostatization_370",
        "rhetorical_device": [
            "hypostatization"
        ],
        "text": "深海での潜水中、私は海底に横たわる沈没船を見て、まるで時が止まった博物館の展示物のようだと感じた。"
    },
    {
        "id": "hypostatization_371",
        "rhetorical_device": [
            "hypostatization"
        ],
        "text": "教室に入ると、生徒たちは机に釘付けになったかのように静かだった。"
    },
    {
        "id": "hypostatization_372",
        "rhetorical_device": [
            "hypostatization"
        ],
        "text": "SNSで流行を追う人々は、まるでプログラムされたボットのように、次々と同じポーズや表情を投稿していった。"
    },
    {
        "id": "hypostatization_373",
        "rhetorical_device": [
            "hypostatization"
        ],
        "text": "酔っ払いたちは、まるで操り人形のように、バーテンダーの一言一句に踊らされていた。"
    },
    {
        "id": "hypostatization_374",
        "rhetorical_device": [
            "hypostatization"
        ],
        "text": "彼女の笑顔は太陽のように明るく、周りの人々を照らしていた。"
    },
    {
        "id": "hypostatization_375",
        "rhetorical_device": [
            "hypostatization"
        ],
        "text": "養蜂家たちは、蜜蜂の群れを操る時、まるで精密な機械を扱うかのように慎重だった。"
    },
    {
        "id": "hypostatization_376",
        "rhetorical_device": [
            "hypostatization"
        ],
        "text": "盆栽の樹形を整える師匠の動きは、まるで大地の息吹そのものだった。"
    },
    {
        "id": "hypostatization_377",
        "rhetorical_device": [
            "hypostatization"
        ],
        "text": "裁判官の冷徹な判断は、まるでコンピュータのアルゴリズムのようだった。"
    },
    {
        "id": "hypostatization_378",
        "rhetorical_device": [
            "hypostatization"
        ],
        "text": "その彫刻家の手は、粘土に触れた瞬間、まるで魔法の杖のように生命を吹き込んでいった。"
    },
    {
        "id": "hypostatization_379",
        "rhetorical_device": [
            "hypostatization"
        ],
        "text": "抹茶を点てる彼女の手つきは、まるで機械のように正確で無駄がなかった。"
    },
    {
        "id": "hypostatization_380",
        "rhetorical_device": [
            "hypostatization"
        ],
        "text": "岩を積み上げる彼の集中力は、まるで重力さえも無視するかのようだった。"
    },
    {
        "id": "hypostatization_381",
        "rhetorical_device": [
            "hypostatization"
        ],
        "text": "スタンドアップコメディアンの言葉は、まるでナイフのように鋭く、観客の心を切り裂いた。笑いの中に隠された真実が、静かに、しかし確実に浸透していった。"
    },
    {
        "id": "hypostatization_382",
        "rhetorical_device": [
            "hypostatization"
        ],
        "text": "その政治家は、まるで風見鶏のように世論の風向きに合わせて意見を変えた。"
    },
    {
        "id": "hypostatization_383",
        "rhetorical_device": [
            "hypostatization"
        ],
        "text": "アルコールは彼の記憶を消しゴムのように消し去り、昨夜の出来事を思い出せなかった。"
    },
    {
        "id": "hypostatization_384",
        "rhetorical_device": [
            "hypostatization"
        ],
        "text": "環境破壊の進む地域を見て、彼の心は砂漠のように乾いていくのを感じた。"
    },
    {
        "id": "hypostatization_385",
        "rhetorical_device": [
            "hypostatization"
        ],
        "text": "政治家の冷徹な判断は、まるで氷の彫像から放たれる冷気のように、国民の心を凍えさせた。"
    },
    {
        "id": "hypostatization_386",
        "rhetorical_device": [
            "hypostatization"
        ],
        "text": "AIの判断ミスで人命が失われた事故について、企業の対応は氷のように冷たく、人間味が欠けていた。"
    },
    {
        "id": "hypostatization_387",
        "rhetorical_device": [
            "hypostatization"
        ],
        "text": "スクラップブッキングに熱中するあまり、彼女の目は写真を切り取るはさみのように鋭く光っていた。"
    },
    {
        "id": "hypostatization_388",
        "rhetorical_device": [
            "hypostatization"
        ],
        "text": "朝の通勤ラッシュ時、人々は電車に詰め込まれ、まるで缶詰のサーディンのようだった。"
    },
    {
        "id": "hypostatization_389",
        "rhetorical_device": [
            "hypostatization"
        ],
        "text": "人工知能の進化は止まることを知らず、まるで永久機関のように日々新たな可能性を生み出していく。"
    },
    {
        "id": "hypostatization_390",
        "rhetorical_device": [
            "hypostatization"
        ],
        "text": "フラッシュモブの参加者たちは、突如として街角に現れた彫像のように、息を潜めて動かなかった。"
    },
    {
        "id": "hypostatization_391",
        "rhetorical_device": [
            "hypostatization"
        ],
        "text": "3Dプリンターは魔法使いのように、無から形を生み出していく。"
    },
    {
        "id": "hypostatization_392",
        "rhetorical_device": [
            "hypostatization"
        ],
        "text": "モダンダンスの舞台で、彼らは機械仕掛けの人形のように精密に動いた。感情を持たない存在のように見えながら、観客の心を揺さぶった。"
    },
    {
        "id": "hypostatization_393",
        "rhetorical_device": [
            "hypostatization"
        ],
        "text": "誕生日パーティーの準備で、母は機械のように効率的に動き回っていた。"
    },
    {
        "id": "hypostatization_394",
        "rhetorical_device": [
            "hypostatization"
        ],
        "text": "エコ製品を売り込む営業マンたちは、まるで機械のように効率的に動き回っていた。"
    },
    {
        "id": "hypostatization_395",
        "rhetorical_device": [
            "hypostatization"
        ],
        "text": "ジャムを作る際、果実をつぶす音は骨を砕くような鈍い音を立てた。"
    },
    {
        "id": "hypostatization_396",
        "rhetorical_device": [
            "hypostatization"
        ],
        "text": "低炭素経済への移行は、まるで巨大な機械のように、ゆっくりと、しかし確実に動き出していた。企業や政府は、その歯車の一部となり、新しいエネルギー源を求めて回転し始めた。"
    },
    {
        "id": "hypostatization_397",
        "rhetorical_device": [
            "hypostatization"
        ],
        "text": "グラフィックデザイナーの手にかかると、単なる線や形が魔法のように生命を吹き込まれ、躍動感あふれる作品へと変貌を遂げる。"
    },
    {
        "id": "hypostatization_398",
        "rhetorical_device": [
            "hypostatization"
        ],
        "text": "ソーシャルメディアのインフルエンサーは、フォロワーという通貨で価値が測られる、生きた広告塔のような存在だった。"
    },
    {
        "id": "hypostatization_399",
        "rhetorical_device": [
            "hypostatization"
        ],
        "text": "自己啓発セミナーの参加者たちは、講師の言葉を吸収しようと、まるで乾いた砂漠の大地のように、渇望に満ちた表情を浮かべていた。"
    },
    {
        "id": "hypostatization_400",
        "rhetorical_device": [
            "hypostatization"
        ],
        "text": "彼女の心は氷のように冷たく、どんな熱い言葉も届かなかった。"
    },
    {
        "id": "hypostatization_401",
        "rhetorical_device": [
            "hypostatization"
        ],
        "text": "彼の拳は鉄のように硬く、相手の顔面に叩きつけられた。"
    },
    {
        "id": "hypostatization_402",
        "rhetorical_device": [
            "hypostatization"
        ],
        "text": "連続殺人事件の被害者たちは、犯人の歪んだゲームボードの上で、無残に倒される将棋の駒のように扱われていた。"
    },
    {
        "id": "hypostatization_403",
        "rhetorical_device": [
            "hypostatization"
        ],
        "text": "教育システムは、子供たちを型にはめて量産する工場のようだった。"
    },
    {
        "id": "hypostatization_404",
        "rhetorical_device": [
            "hypostatization"
        ],
        "text": "古い町並みを守ろうとする住民たちは、まるで生きた盾のように立ちはだかった。"
    },
    {
        "id": "hypostatization_405",
        "rhetorical_device": [
            "hypostatization"
        ],
        "text": "花を育てる彼の手つきは、まるで陶芸家が繊細な作品を形作るかのようだった。"
    },
    {
        "id": "hypostatization_406",
        "rhetorical_device": [
            "hypostatization"
        ],
        "text": "介護施設の廊下には、時間が止まったかのように動かない老人たちが並んでいた。"
    },
    {
        "id": "hypostatization_407",
        "rhetorical_device": [
            "hypostatization"
        ],
        "text": "デジタル化の波に乗り遅れた会社は、まるで化石のように硬直していた。新しい技術を受け入れられない経営陣は、まるでアンティークの装飾品のように、美しくも機能しなかった。"
    },
    {
        "id": "hypostatization_408",
        "rhetorical_device": [
            "hypostatization"
        ],
        "text": "職業訓練校の新入生たちは、まだ磨かれていない原石のようだった。"
    },
    {
        "id": "hypostatization_409",
        "rhetorical_device": [
            "hypostatization"
        ],
        "text": "子供たちはレゴブロックで作った要塞を守るように立ちはだかった。その姿は、プラスチックの兵士たちが命を吹き込まれたかのようだった。"
    },
    {
        "id": "hypostatization_410",
        "rhetorical_device": [
            "hypostatization"
        ],
        "text": "医療現場で働く看護師たちは、まるで休むことを知らない機械のようだった。疲れも見せず、患者のケアに全力を注いでいる。"
    },
    {
        "id": "hypostatization_411",
        "rhetorical_device": [
            "hypostatization"
        ],
        "text": "彼女の指は、ピアノの鍵盤の上を滑るように動き、まるで生命を持った蝶のようだった。"
    },
    {
        "id": "hypostatization_412",
        "rhetorical_device": [
            "hypostatization"
        ],
        "text": "クリスマスイブの夜、サンタクロースを待つ子供たちは、まるでぜんまい仕掛けの人形のように、ベッドの中で身動きひとつしなかった。"
    },
    {
        "id": "hypostatization_413",
        "rhetorical_device": [
            "hypostatization"
        ],
        "text": "編集作業に没頭する彼女の指は、まるでピアノの鍵盤を奏でるかのように、キーボードの上を軽やかに舞っていた。"
    },
    {
        "id": "hypostatization_414",
        "rhetorical_device": [
            "hypostatization"
        ],
        "text": "職人の手は、まるで生きた道具のように革を形作っていった。"
    },
    {
        "id": "hypostatization_415",
        "rhetorical_device": [
            "hypostatization"
        ],
        "text": "盆栽の手入れに熱中するうちに、老人の背中は盆栽の幹のようにねじれ、枝のように細くなっていった。"
    },
    {
        "id": "hypostatization_416",
        "rhetorical_device": [
            "hypostatization"
        ],
        "text": "都会の養蜂家たちは、高層ビルの屋上で忙しく働く蜂たちを見守りながら、自分たちもまた巨大な蜂の巣の中で働く働き蜂のように感じていた。"
    },
    {
        "id": "hypostatization_417",
        "rhetorical_device": [
            "hypostatization"
        ],
        "text": "バレリーナの動きは、まるで風に揺れる柳のようだった。しなやかで、それでいて強靭な意志を感じさせた。"
    },
    {
        "id": "hypostatization_418",
        "rhetorical_device": [
            "hypostatization"
        ],
        "text": "アイスクリームのフレーバーを考える店主の頭脳は、まるで実験室のビーカーのように様々なアイデアを混ぜ合わせていた。"
    },
    {
        "id": "hypostatization_419",
        "rhetorical_device": [
            "hypostatization"
        ],
        "text": "夜空を見上げると、星々は宝石をちりばめたビロードのカーテンのようだった。天の川は、その中で最も輝く真珠の首飾りのように見えた。"
    },
    {
        "id": "hypostatization_420",
        "rhetorical_device": [
            "hypostatization"
        ],
        "text": "老教授の講義は、まるで古い蓄音機から流れる音楽のようだった。学生たちは、その言葉を吸収するのではなく、ただ風化した石碑を眺めるように聞いていた。"
    },
    {
        "id": "hypostatization_421",
        "rhetorical_device": [
            "hypostatization"
        ],
        "text": "クィディッチのシーカーは、まるで空中に浮かぶ探知機のように、スニッチを追い続けた。"
    },
    {
        "id": "hypostatization_422",
        "rhetorical_device": [
            "hypostatization"
        ],
        "text": "アマチュア無線家は、アンテナのように周囲の電波を感知し、常に新しい情報を求めていた。"
    },
    {
        "id": "hypostatization_423",
        "rhetorical_device": [
            "hypostatization"
        ],
        "text": "パーティーの喧騒の中、彼女はまるで壁の装飾品のように無表情で立ち尽くしていた。"
    },
    {
        "id": "hypostatization_424",
        "rhetorical_device": [
            "hypostatization"
        ],
        "text": "フェスの観客は音楽に合わせて揺れる海のようで、波のように体を動かしていた。"
    },
    {
        "id": "hypostatization_425",
        "rhetorical_device": [
            "hypostatization"
        ],
        "text": "熱気球が空を舞う様子は、まるで風に乗った綿菓子のようだった。"
    },
    {
        "id": "hypostatization_426",
        "rhetorical_device": [
            "hypostatization"
        ],
        "text": "新入社員研修で、講師は参加者たちを粘土のように形作ろうとしていた。"
    },
    {
        "id": "hypostatization_427",
        "rhetorical_device": [
            "hypostatization"
        ],
        "text": "ブロガーとしての彼の文章は、まるでデジタルの川のように、読者の心に滑らかに流れ込んでいった。"
    },
    {
        "id": "hypostatization_428",
        "rhetorical_device": [
            "hypostatization"
        ],
        "text": "パーティー会場に入った瞬間、彼は人々の中に溶け込み、まるでカクテルの中の氷のように存在感を失った。"
    },
    {
        "id": "hypostatization_429",
        "rhetorical_device": [
            "hypostatization"
        ],
        "text": "健康診断の結果を見る患者の目は、ガラス玉のように虚ろで、何の感情も映していなかった。"
    },
    {
        "id": "hypostatization_430",
        "rhetorical_device": [
            "hypostatization"
        ],
        "text": "宇宙ステーションの修理作業員は、巨大な機械の中で踊る小さな歯車のように見えた。"
    },
    {
        "id": "hypostatization_431",
        "rhetorical_device": [
            "hypostatization"
        ],
        "text": "岩を積み上げる彼の手つきは、まるで風のように軽やかで、石と一体化したかのようだった。"
    },
    {
        "id": "hypostatization_432",
        "rhetorical_device": [
            "hypostatization"
        ],
        "text": "水耕栽培のトマトは、まるで宝石のように棚に並んでいた。"
    },
    {
        "id": "hypostatization_433",
        "rhetorical_device": [
            "hypostatization"
        ],
        "text": "ベテラン哲学者の論理は、まるで精密な時計のように滞りなく進んでいった。"
    },
    {
        "id": "hypostatization_434",
        "rhetorical_device": [
            "hypostatization"
        ],
        "text": "コンポストの中の微生物たちは、小さな工場労働者のように黙々と有機物を分解していった。"
    },
    {
        "id": "hypostatization_435",
        "rhetorical_device": [
            "hypostatization"
        ],
        "text": "人形師の工房に並ぶ人形たちは、まるで魂の抜け殻のように虚ろな目で来訪者を見つめていた。"
    },
    {
        "id": "hypostatization_436",
        "rhetorical_device": [
            "hypostatization"
        ],
        "text": "持続可能な観光地では、訪れる人々が自然の一部となり、風景に溶け込む木々のように静かに存在感を示していた。"
    },
    {
        "id": "hypostatization_437",
        "rhetorical_device": [
            "hypostatization"
        ],
        "text": "彼女は思い出のスクラップブックを開くたび、紙のように薄くなった記憶が風に舞い上がるような気がした。"
    },
    {
        "id": "hypostatization_438",
        "rhetorical_device": [
            "hypostatization"
        ],
        "text": "太陽光パネルは、まるで現代の魔法の絨毯のように、屋根の上で静かに光を吸収していた。"
    },
    {
        "id": "hypostatization_439",
        "rhetorical_device": [
            "hypostatization"
        ],
        "text": "詩のコンクールで、参加者たちは言葉という武器を手に、文学の戦場で激しく戦っていた。"
    },
    {
        "id": "hypostatization_440",
        "rhetorical_device": [
            "hypostatization"
        ],
        "text": "健康診断で異常を指摘された彼は、まるでガラスの心を持っているかのように脆くなっていた。"
    },
    {
        "id": "hypostatization_441",
        "rhetorical_device": [
            "hypostatization"
        ],
        "text": "paranormal investigationチームのリーダーは、不気味な屋敷の前で鉄の扉のように冷たく立ちはだかった。"
    },
    {
        "id": "hypostatization_442",
        "rhetorical_device": [
            "hypostatization"
        ],
        "text": "その政治家の言葉は、まるで鋭い刃物のように、聴衆の心を切り裂いた。"
    },
    {
        "id": "hypostatization_443",
        "rhetorical_device": [
            "hypostatization"
        ],
        "text": "長距離サイクリストたちは、まるで機械のように正確なペースで山道を登っていった。"
    },
    {
        "id": "hypostatization_444",
        "rhetorical_device": [
            "hypostatization"
        ],
        "text": "3Dプリンターから生まれた製品は、まるでプラスチックの赤ちゃんのように、世界に産み落とされていった。"
    },
    {
        "id": "hypostatization_445",
        "rhetorical_device": [
            "hypostatization"
        ],
        "text": "ボランティア活動に参加した彼女は、まるで機械のように効率的に動き、休憩も取らずに作業を続けた。"
    },
    {
        "id": "hypostatization_446",
        "rhetorical_device": [
            "hypostatization"
        ],
        "text": "新しい環境に適応できない彼は、まるで砂漠に置かれた観葉植物のようだった。"
    },
    {
        "id": "hypostatization_447",
        "rhetorical_device": [
            "hypostatization"
        ],
        "text": "政治家たちは、国民の声を無視し、まるでチェス盤上の駒のように、自分たちの思惑だけで動いていた。"
    },
    {
        "id": "hypostatization_448",
        "rhetorical_device": [
            "hypostatization"
        ],
        "text": "その映画監督の創造力は、まるで火山のように爆発し、観客を圧倒した。"
    },
    {
        "id": "hypostatization_449",
        "rhetorical_device": [
            "hypostatization"
        ],
        "text": "その政治家の言葉は、まるでコンクリートのように固く、冷たかった。低炭素社会への変革を求める市民の声は、その言葉の壁に阻まれ、届くことはなかった。"
    },
    {
        "id": "hypostatization_450",
        "rhetorical_device": [
            "hypostatization"
        ],
        "text": "SNSの炎上は、デジタルの森に燃え広がる野火のように、瞬く間にブランドイメージを焼き尽くした。"
    },
    {
        "id": "hypostatization_451",
        "rhetorical_device": [
            "hypostatization"
        ],
        "text": "アドベンチャーレースの参加者たちは、まるで機械のように正確に動いていた。疲労も痛みも感じないかのように、ただひたすらゴールを目指して前進し続けた。"
    },
    {
        "id": "hypostatization_452",
        "rhetorical_device": [
            "hypostatization"
        ],
        "text": "貧困に苦しむ人々は、社会の底辺で石ころのように転がされていた。"
    },
    {
        "id": "hypostatization_453",
        "rhetorical_device": [
            "hypostatization"
        ],
        "text": "法廷で被告人は、まるで石膏像のように動かず、判決を待っていた。"
    },
    {
        "id": "hypostatization_454",
        "rhetorical_device": [
            "hypostatization"
        ],
        "text": "歴史的建造物の前に立つガイドは、まるで時を超えてきた石像のように不動で、過去の記憶を身にまとっているようだった。"
    },
    {
        "id": "hypostatization_455",
        "rhetorical_device": [
            "hypostatization"
        ],
        "text": "太陽光パネルは、まるで砂漠の中のオアシスのように、荒れ地に新たな生命を吹き込んだ。"
    },
    {
        "id": "hypostatization_456",
        "rhetorical_device": [
            "hypostatization"
        ],
        "text": "彼女の笑顔は、まるで灯台のように、私の暗い気持ちを照らし出した。"
    },
    {
        "id": "hypostatization_457",
        "rhetorical_device": [
            "hypostatization"
        ],
        "text": "バレエ教室の生徒たちは、まるで精巧な音楽箱の中の人形のように、完璧な同期で動いていた。"
    },
    {
        "id": "hypostatization_458",
        "rhetorical_device": [
            "hypostatization"
        ],
        "text": "天体望遠鏡を覗き込む少年の姿は、まるで宇宙に吸い込まれそうな彫像のようだった。"
    },
    {
        "id": "hypostatization_459",
        "rhetorical_device": [
            "hypostatization"
        ],
        "text": "遺伝子は生命の設計図であり、私たちの体という建物を支える柱だ。"
    },
    {
        "id": "hypostatization_460",
        "rhetorical_device": [
            "hypostatization"
        ],
        "text": "田んぼに立つ案山子は、まるで時が止まったかのように動かず、農夫の忠実な石の番人となっていた。"
    },
    {
        "id": "hypostatization_461",
        "rhetorical_device": [
            "hypostatization"
        ],
        "text": "新しい言語を学ぶことは、まるで岩を削るように、忍耐と時間が必要だ。"
    },
    {
        "id": "hypostatization_462",
        "rhetorical_device": [
            "hypostatization"
        ],
        "text": "技能実習生たちは、工場の歯車のように黙々と働いていた。"
    },
    {
        "id": "hypostatization_463",
        "rhetorical_device": [
            "hypostatization"
        ],
        "text": "森の中を歩きながら、彼は木々の間に潜むキノコを探した。その姿は、まるで宝石を探す鉱夫のようだった。"
    },
    {
        "id": "hypostatization_464",
        "rhetorical_device": [
            "hypostatization"
        ],
        "text": "イースターの朝、色とりどりに塗られた卵は、まるで庭に咲いた不思議な花のように、草むらに隠れていた。"
    },
    {
        "id": "hypostatization_465",
        "rhetorical_device": [
            "hypostatization"
        ],
        "text": "映画監督は俳優たちを駒のように動かし、完璧なシーンを作り上げた。"
    },
    {
        "id": "hypostatization_466",
        "rhetorical_device": [
            "hypostatization"
        ],
        "text": "スクリーンに映し出される俳優たちは、観客の感情を操る糸のない操り人形のようだった。"
    },
    {
        "id": "hypostatization_467",
        "rhetorical_device": [
            "hypostatization"
        ],
        "text": "極地探検の最中、吹雪に立ち向かう彼らの姿は、まるで氷の彫刻のように凛としていた。"
    },
    {
        "id": "hypostatization_468",
        "rhetorical_device": [
            "hypostatization"
        ],
        "text": "ワインの味わいを語る彼の言葉は、まるで石で作られた舌から発せられているかのように冷たく無機質だった。"
    },
    {
        "id": "hypostatization_469",
        "rhetorical_device": [
            "hypostatization"
        ],
        "text": "満員電車の中で、乗客たちはまるでサーディンの缶詰のように押し込められていた。"
    },
    {
        "id": "hypostatization_470",
        "rhetorical_device": [
            "hypostatization"
        ],
        "text": "マクラメの糸は、彼女の指先で生命を宿したかのように踊り、複雑な模様を紡ぎ出していった。"
    },
    {
        "id": "hypostatization_471",
        "rhetorical_device": [
            "hypostatization"
        ],
        "text": "エネルギー効率の悪い古い家電は、まるで電気を飲み込む怪物のように、電力を浪費していた。"
    },
    {
        "id": "hypostatization_472",
        "rhetorical_device": [
            "hypostatization"
        ],
        "text": "天文学者たちは、望遠鏡を覗き込みながら、まるで宇宙の秘密を解読しようとする暗号解読者のように熱心だった。"
    },
    {
        "id": "hypostatization_473",
        "rhetorical_device": [
            "hypostatization"
        ],
        "text": "AIの判断は冷徹で、まるでコンピューターのチップのように感情を持たなかった。"
    },
    {
        "id": "hypostatization_474",
        "rhetorical_device": [
            "hypostatization"
        ],
        "text": "環境保護団体の会議で、彼は岩のように動じない表情で自分の意見を述べ続けた。"
    },
    {
        "id": "hypostatization_475",
        "rhetorical_device": [
            "hypostatization"
        ],
        "text": "深夜番組のリスナーたちは、DJの声に導かれる木の葉のように、静かに夜の街を漂っていた。それぞれの物語が、電波に乗って交錯する。"
    },
    {
        "id": "hypostatization_476",
        "rhetorical_device": [
            "hypostatization"
        ],
        "text": "その俳優の演技は木彫りの人形のように硬く、感情が伝わってこなかった。"
    },
    {
        "id": "hypostatization_477",
        "rhetorical_device": [
            "hypostatization"
        ],
        "text": "サファリツアーで見た象の群れは、まるで大地から生えた灰色の丘のようだった。"
    },
    {
        "id": "hypostatization_478",
        "rhetorical_device": [
            "hypostatization"
        ],
        "text": "彼女は写真を撮る瞬間、まるで大理石の彫像のように静止した。"
    },
    {
        "id": "hypostatization_479",
        "rhetorical_device": [
            "hypostatization"
        ],
        "text": "古文書を扱う学芸員の指先は、まるでピンセットのように繊細で正確だった。"
    },
    {
        "id": "hypostatization_480",
        "rhetorical_device": [
            "hypostatization"
        ],
        "text": "ワークライフバランスを崩した彼女は、まるでゼンマイ仕掛けの人形のように、機械的に日々を過ごしていた。"
    },
    {
        "id": "hypostatization_481",
        "rhetorical_device": [
            "hypostatization"
        ],
        "text": "古い羊皮紙を広げる歴史家の手つきは、まるで蝶の羽のように軽やかで慎重だった。"
    },
    {
        "id": "hypostatization_482",
        "rhetorical_device": [
            "hypostatization"
        ],
        "text": "彼女は料理本を開いたまま、まるで石像のように動かなかった。レシピの難しさに圧倒されたようだ。"
    },
    {
        "id": "hypostatization_483",
        "rhetorical_device": [
            "hypostatization"
        ],
        "text": "刑事は犯罪現場を調べながら、まるでデータを処理するコンピューターのように冷静に分析していった。"
    },
    {
        "id": "hypostatization_484",
        "rhetorical_device": [
            "hypostatization"
        ],
        "text": "彼女のアイデアは、スクラップブックの中で眠る切り抜きのように、誰にも気づかれないまま埋もれていった。"
    },
    {
        "id": "hypostatization_485",
        "rhetorical_device": [
            "hypostatization"
        ],
        "text": "ゲームの世界に没頭するプレイヤーの意識は、まるでピクセルに変換されたかのように、現実世界から切り離されていった。"
    },
    {
        "id": "hypostatization_486",
        "rhetorical_device": [
            "hypostatization"
        ],
        "text": "人類学者は、古代の遺跡を前に氷のように凍りついた。その瞬間、時間さえも止まったかのようだった。"
    },
    {
        "id": "hypostatization_487",
        "rhetorical_device": [
            "hypostatization"
        ],
        "text": "監督の鋭い指示は、俳優たちの演技を彫刻刀のように削り出していった。一つ一つのシーンが、まるで大理石から生まれる芸術作品のように形作られていく。"
    },
    {
        "id": "hypostatization_488",
        "rhetorical_device": [
            "hypostatization"
        ],
        "text": "老人ホームの入居者たちは、まるで棚に並べられた古い本のように、静かに日々を過ごしていた。"
    },
    {
        "id": "hypostatization_489",
        "rhetorical_device": [
            "hypostatization"
        ],
        "text": "彼女の歌声は、まるで宝石のように会場全体を輝かせた。"
    },
    {
        "id": "hypostatization_490",
        "rhetorical_device": [
            "hypostatization"
        ],
        "text": "動物園の檻の中で、ライオンは石像のように動かなかった。かつての王者の威厳は、今や博物館の展示品のように色あせていた。"
    },
    {
        "id": "hypostatization_491",
        "rhetorical_device": [
            "hypostatization"
        ],
        "text": "石鹸作りの匠の手は、長年の経験で磨かれた道具のようにしなやかで力強かった。"
    },
    {
        "id": "hypostatization_492",
        "rhetorical_device": [
            "hypostatization"
        ],
        "text": "ベテランのパラグライダーは、鷹のように空を支配し、風を自在に操っているようだった。"
    },
    {
        "id": "hypostatization_493",
        "rhetorical_device": [
            "hypostatization"
        ],
        "text": "祭りの山車が通り過ぎると、群衆は波のように揺れ動いた。人々は海の泡沫となり、祭りという大海原に飲み込まれていった。"
    },
    {
        "id": "hypostatization_494",
        "rhetorical_device": [
            "hypostatization"
        ],
        "text": "彼の心は鋼鉄のように冷たく、地域経済の衰退を前にしても動じなかった。"
    },
    {
        "id": "hypostatization_495",
        "rhetorical_device": [
            "hypostatization"
        ],
        "text": "彼女は緑茶を啜りながら、氷のような冷たい目つきで相手を見つめた。"
    },
    {
        "id": "hypostatization_496",
        "rhetorical_device": [
            "hypostatization"
        ],
        "text": "抹茶の粉は、緑色の雪のように茶碗に舞い降りた。"
    },
    {
        "id": "hypostatization_497",
        "rhetorical_device": [
            "hypostatization"
        ],
        "text": "彼の心は、長年の失恋によって石のように固くなっていた。"
    },
    {
        "id": "hypostatization_498",
        "rhetorical_device": [
            "hypostatization"
        ],
        "text": "パラグライダーが空を舞う様子は、まるで風に乗った葉っぱのようだった。"
    },
    {
        "id": "hypostatization_499",
        "rhetorical_device": [
            "hypostatization"
        ],
        "text": "哲学者の言葉は、まるで鋼鉄の壁のように、聴衆の心に跳ね返っていった。"
    },
    {
        "id": "hypostatization_500",
        "rhetorical_device": [
            "hypostatization"
        ],
        "text": "映画のエキストラたちは、背景の壁紙のように存在感を消していた。しかし、その一人一人が、この作品という絵画を完成させる重要な色彩だった。"
    },
    {
        "id": "hypostatization_501",
        "rhetorical_device": [
            "hypostatization"
        ],
        "text": "陶芸家の手は、長年の経験で磨かれた道具のようだった。粘土を触れば、まるで魔法のように形が生まれた。"
    },
    {
        "id": "hypostatization_502",
        "rhetorical_device": [
            "hypostatization"
        ],
        "text": "ジェンダーの壁は、まるで鉄のカーテンのように社会を分断していた。"
    },
    {
        "id": "hypostatization_503",
        "rhetorical_device": [
            "hypostatization"
        ],
        "text": "イースターエッグハントで、子供たちは宝石を探す小さな探検家のように、庭中を這いまわっていた。"
    },
    {
        "id": "hypostatization_504",
        "rhetorical_device": [
            "hypostatization"
        ],
        "text": "発酵中のヨーグルトは、まるで生きた彫刻のように、ゆっくりと形を変えていった。"
    },
    {
        "id": "hypostatization_505",
        "rhetorical_device": [
            "hypostatization"
        ],
        "text": "観光地の夜景は、まるで宝石箱のように輝いていた。人々は、その光に魅せられ、まるで蛾のように集まってきた。"
    },
    {
        "id": "hypostatization_506",
        "rhetorical_device": [
            "hypostatization"
        ],
        "text": "クラフトビールの味わいに酔いしれ、彼の舌は最高級の測定器と化していった。"
    },
    {
        "id": "hypostatization_507",
        "rhetorical_device": [
            "hypostatization"
        ],
        "text": "最新の医療技術を前に、古い治療法は化石のように固まっていった。"
    },
    {
        "id": "hypostatization_508",
        "rhetorical_device": [
            "hypostatization"
        ],
        "text": "ピアニストの演奏は、まるで滝のように途切れることなく、聴衆の心に流れ込んでいった。"
    }
]